Workbook

Sheet PL
A1: Sno | B1: Date | C1: Month | D1: Year | E1: Deal Wins(N) | F1: Contract | G1: MOM-Growth | H1: Income | I1: Expense | J1: Profit | K1: MOM-Growth
A2: 1 | B2: 45901 | C2: =TEXT(B2,"mmmm") -> September | D2: =YEAR(B2) -> 2025 | E2: =COUNTIFS('Order Book'!C:C,">="&B2,'Order Book'!C:C,"<="&EOMONTH(B2,0)) -> 6 | F2: =SUMIFS('Order Book'!M:M,'Order Book'!C:C,">="&B2,'Order Book'!C:C,"<="&EOMONTH(B2,0)) -> 460000 | H2: =SUMIFS(Income!K:K,Income!C:C,">="&B2,Income!C:C,"<="&EOMONTH(B2,0)) -> 85000 | I2: =SUMIFS(Expenses!G:G,Expenses!B:B,">="&B2,Expenses!B:B,"<="&EOMONTH(B2,0)) -> 96060.63 | J2: =H2-I2 -> -11060.63
A3: =A2+1 -> 2 | B3: 45931 | C3: =TEXT(B3,"mmmm") -> October | D3: =YEAR(B3) -> 2025 | E3: =COUNTIFS('Order Book'!C:C,">="&B3,'Order Book'!C:C,"<="&EOMONTH(B3,0)) -> 7 | F3: =SUMIFS('Order Book'!M:M,'Order Book'!C:C,">="&B3,'Order Book'!C:C,"<="&EOMONTH(B3,0)) -> 1075500 | G3: =IFERROR(ABS(F3/F2)-1,0) -> 1.3380435 | H3: =SUMIFS(Income!K:K,Income!C:C,">="&B3,Income!C:C,"<="&EOMONTH(B3,0)) -> 397500 | I3: =SUMIFS(Expenses!G:G,Expenses!B:B,">="&B3,Expenses!B:B,"<="&EOMONTH(B3,0)) -> 337681.02 | J3: =H3-I3 -> 59818.98 | K3: =IFERROR(ABS(J3/J2)-1,0) -> 4.4082796
A4: =A3+1 -> 3 | B4: 45962 | C4: =TEXT(B4,"mmmm") -> November | D4: =YEAR(B4) -> 2025 | E4: =COUNTIFS('Order Book'!C:C,">="&B4,'Order Book'!C:C,"<="&EOMONTH(B4,0)) -> 9 | F4: =SUMIFS('Order Book'!M:M,'Order Book'!C:C,">="&B4,'Order Book'!C:C,"<="&EOMONTH(B4,0)) -> 1307500 | G4: =IFERROR(ABS(F4/F3)-1,0) -> 0.21571362 | H4: =SUMIFS(Income!K:K,Income!C:C,">="&B4,Income!C:C,"<="&EOMONTH(B4,0)) -> 666838.42 | I4: =SUMIFS(Expenses!G:G,Expenses!B:B,">="&B4,Expenses!B:B,"<="&EOMONTH(B4,0)) -> 415195.03 | J4: =H4-I4 -> 251643.39 | K4: =IFERROR(ABS(J4/J3)-1,0) -> 3.2067483
A5: =A4+1 -> 4 | B5: 45992 | C5: =TEXT(B5,"mmmm") -> December | D5: =YEAR(B5) -> 2025 | E5: =COUNTIFS('Order Book'!C:C,">="&B5,'Order Book'!C:C,"<="&EOMONTH(B5,0)) -> 7 | F5: =SUMIFS('Order Book'!M:M,'Order Book'!C:C,">="&B5,'Order Book'!C:C,"<="&EOMONTH(B5,0)) -> 730000 | G5: =IFERROR(ABS(F5/F4)-1,0) -> -0.4416826 | H5: =SUMIFS(Income!K:K,Income!C:C,">="&B5,Income!C:C,"<="&EOMONTH(B5,0)) -> 587000 | I5: =SUMIFS(Expenses!G:G,Expenses!B:B,">="&B5,Expenses!B:B,"<="&EOMONTH(B5,0)) -> 382480.84 | J5: =H5-I5 -> 204519.16 | K5: =IFERROR(ABS(J5/J4)-1,0) -> -0.18726591
A6: =A5+1 -> 5 | B6: 46023 | C6: =TEXT(B6,"mmmm") -> January | D6: =YEAR(B6) -> 2026 | E6: =COUNTIFS('Order Book'!C:C,">="&B6,'Order Book'!C:C,"<="&EOMONTH(B6,0)) -> 2 | F6: =SUMIFS('Order Book'!M:M,'Order Book'!C:C,">="&B6,'Order Book'!C:C,"<="&EOMONTH(B6,0)) -> 145000 | G6: =IFERROR(ABS(F6/F5)-1,0) -> -0.80136986 | H6: =SUMIFS(Income!K:K,Income!C:C,">="&B6,Income!C:C,"<="&EOMONTH(B6,0)) -> 284500 | I6: =SUMIFS(Expenses!G:G,Expenses!B:B,">="&B6,Expenses!B:B,"<="&EOMONTH(B6,0)) -> 326461.51 | J6: =H6-I6 -> -41961.51 | K6: =IFERROR(ABS(J6/J5)-1,0) -> -0.79482847
A7: =A6+1 -> 6 | B7: 46054 | C7: =TEXT(B7,"mmmm") -> February | D7: =YEAR(B7) -> 2026 | E7: =COUNTIFS('Order Book'!C:C,">="&B7,'Order Book'!C:C,"<="&EOMONTH(B7,0)) -> 7 | F7: =SUMIFS('Order Book'!M:M,'Order Book'!C:C,">="&B7,'Order Book'!C:C,"<="&EOMONTH(B7,0)) -> 894510 | G7: =IFERROR(ABS(F7/F6)-1,0) -> 5.1690345 | H7: =SUMIFS(Income!K:K,Income!C:C,">="&B7,Income!C:C,"<="&EOMONTH(B7,0)) -> 646383.9 | I7: =SUMIFS(Expenses!G:G,Expenses!B:B,">="&B7,Expenses!B:B,"<="&EOMONTH(B7,0)) -> 461834.11 | J7: =H7-I7 -> 184549.79 | K7: =IFERROR(ABS(J7/J6)-1,0) -> 3.3980731
A8: =A7+1 -> 7 | B8: 46082 | C8: =TEXT(B8,"mmmm") -> March | D8: =YEAR(B8) -> 2026 | E8: =COUNTIFS('Order Book'!C:C,">="&B8,'Order Book'!C:C,"<="&EOMONTH(B8,0)) -> 1 | F8: =SUMIFS('Order Book'!M:M,'Order Book'!C:C,">="&B8,'Order Book'!C:C,"<="&EOMONTH(B8,0)) -> 95000 | G8: =IFERROR(ABS(F8/F7)-1,0) -> -0.8937966 | H8: =SUMIFS(Income!K:K,Income!C:C,">="&B8,Income!C:C,"<="&EOMONTH(B8,0)) -> 105000 | I8: =SUMIFS(Expenses!G:G,Expenses!B:B,">="&B8,Expenses!B:B,"<="&EOMONTH(B8,0)) -> 420064.18 | J8: =H8-I8 -> -315064.18 | K8: =IFERROR(ABS(J8/J7)-1,0) -> 0.70720422
A9: =A8+1 -> 8 | B9: 46113 | C9: =TEXT(B9,"mmmm") -> April | D9: =YEAR(B9) -> 2026 | E9: =COUNTIFS('Order Book'!C:C,">="&B9,'Order Book'!C:C,"<="&EOMONTH(B9,0)) -> 0 | F9: =SUMIFS('Order Book'!M:M,'Order Book'!C:C,">="&B9,'Order Book'!C:C,"<="&EOMONTH(B9,0)) -> 0 | G9: =IFERROR(ABS(F9/F8)-1,0) -> -1 | H9: =SUMIFS(Income!K:K,Income!C:C,">="&B9,Income!C:C,"<="&EOMONTH(B9,0)) -> 0 | I9: =SUMIFS(Expenses!G:G,Expenses!B:B,">="&B9,Expenses!B:B,"<="&EOMONTH(B9,0)) -> 0 | J9: =H9-I9 -> 0 | K9: =IFERROR(ABS(J9/J8)-1,0) -> -1
A10: =A9+1 -> 9 | B10: 46143 | C10: =TEXT(B10,"mmmm") -> May | D10: =YEAR(B10) -> 2026 | E10: =COUNTIFS('Order Book'!C:C,">="&B10,'Order Book'!C:C,"<="&EOMONTH(B10,0)) -> 0 | F10: =SUMIFS('Order Book'!M:M,'Order Book'!C:C,">="&B10,'Order Book'!C:C,"<="&EOMONTH(B10,0)) -> 0 | G10: =IFERROR(ABS(F10/F9)-1,0) -> 0 | H10: =SUMIFS(Income!K:K,Income!C:C,">="&B10,Income!C:C,"<="&EOMONTH(B10,0)) -> 0 | I10: =SUMIFS(Expenses!G:G,Expenses!B:B,">="&B10,Expenses!B:B,"<="&EOMONTH(B10,0)) -> 0 | J10: =H10-I10 -> 0 | K10: =IFERROR(ABS(J10/J9)-1,0) -> 0
A11: =A10+1 -> 10 | B11: 46174 | C11: =TEXT(B11,"mmmm") -> June | D11: =YEAR(B11) -> 2026 | E11: =COUNTIFS('Order Book'!C:C,">="&B11,'Order Book'!C:C,"<="&EOMONTH(B11,0)) -> 0 | F11: =SUMIFS('Order Book'!M:M,'Order Book'!C:C,">="&B11,'Order Book'!C:C,"<="&EOMONTH(B11,0)) -> 0 | G11: =IFERROR(ABS(F11/F10)-1,0) -> 0 | H11: =SUMIFS(Income!K:K,Income!C:C,">="&B11,Income!C:C,"<="&EOMONTH(B11,0)) -> 0 | I11: =SUMIFS(Expenses!G:G,Expenses!B:B,">="&B11,Expenses!B:B,"<="&EOMONTH(B11,0)) -> 0 | J11: =H11-I11 -> 0 | K11: =IFERROR(ABS(J11/J10)-1,0) -> 0
A12: =A11+1 -> 11 | B12: 46204 | C12: =TEXT(B12,"mmmm") -> July | D12: =YEAR(B12) -> 2026 | E12: =COUNTIFS('Order Book'!C:C,">="&B12,'Order Book'!C:C,"<="&EOMONTH(B12,0)) -> 0 | F12: =SUMIFS('Order Book'!M:M,'Order Book'!C:C,">="&B12,'Order Book'!C:C,"<="&EOMONTH(B12,0)) -> 0 | G12: =IFERROR(ABS(F12/F11)-1,0) -> 0 | H12: =SUMIFS(Income!K:K,Income!C:C,">="&B12,Income!C:C,"<="&EOMONTH(B12,0)) -> 0 | I12: =SUMIFS(Expenses!G:G,Expenses!B:B,">="&B12,Expenses!B:B,"<="&EOMONTH(B12,0)) -> 0 | J12: =H12-I12 -> 0 | K12: =IFERROR(ABS(J12/J11)-1,0) -> 0
A13: =A12+1 -> 12 | B13: 46235 | C13: =TEXT(B13,"mmmm") -> August | D13: =YEAR(B13) -> 2026 | E13: =COUNTIFS('Order Book'!C:C,">="&B13,'Order Book'!C:C,"<="&EOMONTH(B13,0)) -> 0 | F13: =SUMIFS('Order Book'!M:M,'Order Book'!C:C,">="&B13,'Order Book'!C:C,"<="&EOMONTH(B13,0)) -> 0 | G13: =IFERROR(ABS(F13/F12)-1,0) -> 0 | H13: =SUMIFS(Income!K:K,Income!C:C,">="&B13,Income!C:C,"<="&EOMONTH(B13,0)) -> 0 | I13: =SUMIFS(Expenses!G:G,Expenses!B:B,">="&B13,Expenses!B:B,"<="&EOMONTH(B13,0)) -> 0 | J13: =H13-I13 -> 0 | K13: =IFERROR(ABS(J13/J12)-1,0) -> 0
A14: =A13+1 -> 13 | B14: 46266 | C14: =TEXT(B14,"mmmm") -> September | D14: =YEAR(B14) -> 2026 | E14: =COUNTIFS('Order Book'!C:C,">="&B14,'Order Book'!C:C,"<="&EOMONTH(B14,0)) -> 0 | F14: =SUMIFS('Order Book'!M:M,'Order Book'!C:C,">="&B14,'Order Book'!C:C,"<="&EOMONTH(B14,0)) -> 0 | G14: =IFERROR(ABS(F14/F13)-1,0) -> 0 | H14: =SUMIFS(Income!K:K,Income!C:C,">="&B14,Income!C:C,"<="&EOMONTH(B14,0)) -> 0 | I14: =SUMIFS(Expenses!G:G,Expenses!B:B,">="&B14,Expenses!B:B,"<="&EOMONTH(B14,0)) -> 0 | J14: =H14-I14 -> 0 | K14: =IFERROR(ABS(J14/J13)-1,0) -> 0
... A17: =A16+1 -> 16 | B17: 46357 | C17: =TEXT(B17,"mmmm") -> December | D17: =YEAR(B17) -> 2026 | E17: =COUNTIFS('Order Book'!C:C,">="&B17,'Order Book'!C:C,"<="&EOMONTH(B17,0)) -> 0 | F17: =SUMIFS('Order Book'!M:M,'Order Book'!C:C,">="&B17,'Order Book'!C:C,"<="&EOMONTH(B17,0)) -> 0 | G17: =IFERROR(ABS(F17/F16)-1,0) -> 0 | H17: =SUMIFS(Income!K:K,Income!C:C,">="&B17,Income!C:C,"<="&EOMONTH(B17,0)) -> 0 | I17: =SUMIFS(Expenses!G:G,Expenses!B:B,">="&B17,Expenses!B:B,"<="&EOMONTH(B17,0)) -> 0 | J17: =H17-I17 -> 0 | K17: =IFERROR(ABS(J17/J16)-1,0) -> 0
C19: Total | E19: =SUM(E2:E17) -> 39 | F19: =SUM(F2:F17) -> 4707510
C20: Pending Amount | F20: =F19-H20 -> 1935287.7 | H20: =SUM(H2:H17) -> 2772222.3 | I20: =SUM(I2:I17) -> 2439777.3 | J20: =SUM(J2:J17) -> 332445

Sheet How to
A1: ArgosMob Tech & AI Pvt LTD, Feb 2026, P/L Distribution
A2: Total profit | B2: =PL!J7+125000 -> 309549.79
A3: Director Salary | B3: 125000
A4: Monthly expenses Adjustments | B4: 4259.78
A5: Net Profit | B5: =B2-B3-B4 -> 180290.01
A7: Profit/Partner | B7: =B5/5 -> 36058.002
A8: Salary+Profit | B8: =B7+25000 -> 61058.002
A13: 46054 | B13: Salary | C13: Adjustment | D13: Profit | E13: Settlement Amout | F13: Total
A14: Chandan | B14: 25000 | C14: =Expenses!P2 -> 30882 | D14: =$B$7 -> 36058.002 | E14: =D14-C14 -> 5176.002 | F14: =D14+B14 -> 61058.002
A15: Krishan | B15: 25000 | C15: =Expenses!P3 -> 44061.18 | D15: =$B$7 -> 36058.002 | E15: =D15-C15 -> -8003.178 | F15: =D15+B15 -> 61058.002
A16: Rishab | B16: 25000 | C16: =Expenses!P4 -> 48151.98 | D16: =$B$7 -> 36058.002 | E16: =D16-C16 -> -12093.978 | F16: =D16+B16 -> 61058.002
A17: Vansh | B17: 25000 | C17: =Expenses!P5 -> 31058 | D17: =$B$7 -> 36058.002 | E17: =D17-C17 -> 5000.002 | F17: =D17+B17 -> 61058.002
A18: Dr Chadha | B18: 12500 | D18: =D17/2 -> 18029.001 | E18: =D18-C18 -> 18029.001 | F18: =D18+B18 -> 30529.001
A19: Jitender sir | B19: 12500 | D19: =D18 -> 18029.001 | E19: =D19-C19 -> 18029.001 | F19: =D19+B19 -> 30529.001
A21: Total | B21: =SUM(B14:B19) -> 125000 | C21: =SUM(C14:C19) -> 154153.16 | D21: =SUM(D14:D19) -> 180290.01 | E21: =SUM(E14:E19) -> 26136.85 | F21: =SUM(F14:F19) -> 305290.01

Sheet Daily Tracker
A1: Sno | B1: Week Number | C1: Day | D1: Date | E1: Revenue | F1: Expenses | G1: New Orders | H1: Change in old project
A2: 1 | B2: =WEEKNUM(D2) -> 5 | C2: =TEXT(D2,"dddd") -> Tuesday | D2: 46049 | E2: =SUMIFS(Income!K:K,Income!C:C,'Daily Tracker'!D2) -> 50000 | F2: =SUMIFS(Expenses!G:G,Expenses!B:B,'Daily Tracker'!D2) -> 47191.47 | G2: =SUMIFS('Order Book'!K:K,'Order Book'!C:C,'Daily Tracker'!D2) -> 0
A3: 2 | B3: =WEEKNUM(D3) -> 5 | C3: =TEXT(D3,"dddd") -> Wednesday | D3: 46050 | E3: =SUMIFS(Income!K:K,Income!C:C,'Daily Tracker'!D3) -> 0 | F3: =SUMIFS(Expenses!G:G,Expenses!B:B,'Daily Tracker'!D3) -> 0 | G3: =SUMIFS('Order Book'!K:K,'Order Book'!C:C,'Daily Tracker'!D3) -> 0
A4: 3 | B4: =WEEKNUM(D4) -> 5 | C4: =TEXT(D4,"dddd") -> Thursday | D4: 46051 | E4: =SUMIFS(Income!K:K,Income!C:C,'Daily Tracker'!D4) -> 0 | F4: =SUMIFS(Expenses!G:G,Expenses!B:B,'Daily Tracker'!D4) -> 6235 | G4: =SUMIFS('Order Book'!K:K,'Order Book'!C:C,'Daily Tracker'!D4) -> 0
A5: 4 | B5: =WEEKNUM(D5) -> 5 | C5: =TEXT(D5,"dddd") -> Friday | D5: 46052 | E5: =SUMIFS(Income!K:K,Income!C:C,'Daily Tracker'!D5) -> 0 | F5: =SUMIFS(Expenses!G:G,Expenses!B:B,'Daily Tracker'!D5) -> 36727 | G5: =SUMIFS('Order Book'!K:K,'Order Book'!C:C,'Daily Tracker'!D5) -> 0
A6: 5 | B6: =WEEKNUM(D6) -> 5 | C6: =TEXT(D6,"dddd") -> Saturday | D6: 46053 | E6: =SUMIFS(Income!K:K,Income!C:C,'Daily Tracker'!D6) -> 0 | F6: =SUMIFS(Expenses!G:G,Expenses!B:B,'Daily Tracker'!D6) -> 1256.58 | G6: =SUMIFS('Order Book'!K:K,'Order Book'!C:C,'Daily Tracker'!D6) -> 0
A7: 6 | B7: =WEEKNUM(D7) -> 6 | C7: =TEXT(D7,"dddd") -> Sunday | D7: 46054 | E7: =SUMIFS(Income!K:K,Income!C:C,'Daily Tracker'!D7) -> 0 | F7: =SUMIFS(Expenses!G:G,Expenses!B:B,'Daily Tracker'!D7) -> 0 | G7: =SUMIFS('Order Book'!K:K,'Order Book'!C:C,'Daily Tracker'!D7) -> 0
A8: 7 | B8: =WEEKNUM(D8) -> 6 | C8: =TEXT(D8,"dddd") -> Monday | D8: 46055 | E8: =SUMIFS(Income!K:K,Income!C:C,'Daily Tracker'!D8) -> 75000 | F8: =SUMIFS(Expenses!G:G,Expenses!B:B,'Daily Tracker'!D8) -> 14029.6 | G8: =SUMIFS('Order Book'!K:K,'Order Book'!C:C,'Daily Tracker'!D8) -> 400000
A9: 8 | B9: =WEEKNUM(D9) -> 6 | C9: =TEXT(D9,"dddd") -> Tuesday | D9: 46056 | E9: =SUMIFS(Income!K:K,Income!C:C,'Daily Tracker'!D9) -> 0 | F9: =SUMIFS(Expenses!G:G,Expenses!B:B,'Daily Tracker'!D9) -> 349 | G9: =SUMIFS('Order Book'!K:K,'Order Book'!C:C,'Daily Tracker'!D9) -> 0
A10: 9 | B10: =WEEKNUM(D10) -> 6 | C10: =TEXT(D10,"dddd") -> Wednesday | D10: 46057 | E10: =SUMIFS(Income!K:K,Income!C:C,'Daily Tracker'!D10) -> 0 | F10: =SUMIFS(Expenses!G:G,Expenses!B:B,'Daily Tracker'!D10) -> 590 | G10: =SUMIFS('Order Book'!K:K,'Order Book'!C:C,'Daily Tracker'!D10) -> 25000
A11: 10 | B11: =WEEKNUM(D11) -> 6 | C11: =TEXT(D11,"dddd") -> Thursday | D11: 46058 | E11: =SUMIFS(Income!K:K,Income!C:C,'Daily Tracker'!D11) -> 0 | F11: =SUMIFS(Expenses!G:G,Expenses!B:B,'Daily Tracker'!D11) -> 25300 | G11: =SUMIFS('Order Book'!K:K,'Order Book'!C:C,'Daily Tracker'!D11) -> 50000
A12: 11 | B12: =WEEKNUM(D12) -> 6 | C12: =TEXT(D12,"dddd") -> Friday | D12: 46059 | E12: =SUMIFS(Income!K:K,Income!C:C,'Daily Tracker'!D12) -> 25000 | F12: =SUMIFS(Expenses!G:G,Expenses!B:B,'Daily Tracker'!D12) -> 350 | G12: =SUMIFS('Order Book'!K:K,'Order Book'!C:C,'Daily Tracker'!D12) -> 0
A13: 12 | B13: =WEEKNUM(D13) -> 6 | C13: =TEXT(D13,"dddd") -> Saturday | D13: 46060 | E13: =SUMIFS(Income!K:K,Income!C:C,'Daily Tracker'!D13) -> 30000 | F13: =SUMIFS(Expenses!G:G,Expenses!B:B,'Daily Tracker'!D13) -> 4517.7 | G13: =SUMIFS('Order Book'!K:K,'Order Book'!C:C,'Daily Tracker'!D13) -> 0
... A66: 65 | B66: =WEEKNUM(D66) -> 14 | C66: =TEXT(D66,"dddd") -> Wednesday | D66: 46113 | E66: =SUMIFS(Income!K:K,Income!C:C,'Daily Tracker'!D66) -> 0 | F66: =SUMIFS(Expenses!G:G,Expenses!B:B,'Daily Tracker'!D66) -> 0 | G66: =SUMIFS('Order Book'!K:K,'Order Book'!C:C,'Daily Tracker'!D66) -> 0

Sheet Staff
A1: Sno | B1: Team | C1: Name | D1: Salary | E1: Location | F1: Comments | G1: DOJ
A2: 1 | B2: HR | C2: Ravleen Kaur | D2: 15000 | E2: Office | G2: DOJ- 27-1-2026 | H2: 17500
A3: 2 | B3: Mobile | C3: Prashant | D3: 15000 | E3: Office | F3: DOJ- 28-10-2025 | G3: 45958 | H3: 12000
A4: 3 | B4: Mobile | C4: Aditya Jain | D4: 31000 | E4: Office | F4: DOJ- 27-1-2026 | G4: DOJ- 27-1-2026 | H4: 35000
A5: 4 | B5: Mobile | C5: Ishika Sharma | D5: 25000 | E5: Office | H5: 25000
A6: 5 | B6: Mobile | C6: Shubham Dubey | D6: 15000 | E6: Office | H6: 10000
A7: 6 | B7: Sales | C7: Haider | D7: 45000 | E7: Office | F7: DOJ- 27-10-2025 | G7: 45909 | H7: 45000
A8: 7 | B8: Sales | C8: Avani Shree | D8: 30000 | E8: Office | G8: 46069 | H8: 13000
A9: 8 | B9: Mobile+Back End | C9: Priyanka | D9: 30000 | E9: Office | F9: DOJ- 10-11-2025 | G9: 45894 | H9: 30000
A10: 9 | B10: Web - Back end | C10: Dev kumar Sharma | D10: 40000 | E10: WFH | G10: 45957 | H10: 40000
A11: 10 | B11: Video Editor | C11: Resource 1 | E11: Office
A12: 11 | B12: Tester | C12: Ranjeet | D12: 20000 | E12: Office | G12: 46090
A13: 12 | B13: Sales | C13: Akansha Giri | D13: 33000 | E13: Office | H13: 15000
A14: 13 | B14: Sales | C14: Yash Vohra | D14: 0 | E14: WFH
A15: 14 | B15: Sales | C15: Asmita Pandey | D15: 45000 | E15: Office | G15: 46093
C26: Total Salary | D26: =SUM(D2:D15) -> 344000 | E26: 240000
C27: Office rent | D27: 32000 | E27: 32000
C28: Misc | D28: 18000 | E28: 18000
C29: Marketing | D29: 180000
C30: IT subscriptions | D30: 4000
C33: Total Monthly Expenses | D33: =SUM(D26:D30) -> 578000 | F33: =D33+125000 -> 703000
C34: Annual Expenses | D34: =D33*12 -> 6936000 | E34: 50lac | F34: =F33/0.4 -> 1757500
C35: Per partner Expenses | D35: =D33/4 -> 144500

Sheet Feb expenses
A1: Feb Expenses
A2: Sno | B2: Team | C2: Name | D2: Salary | E2: Location | F2: DOJ
A3: 1 | B3: Mobile | C3: Prashant | D3: 10000 | E3: Office
A4: =A3+1 -> 2 | B4: Mobile | C4: Ishika Sharma | D4: =G4/30*25000 -> 14166.667 | E4: Office | F4: 46036 | G4: =_xlfn.DAYS(H4,F4) -> 17 | H4: 46053
A5: =A4+1 -> 3 | B5: Mobile | C5: Shubham Dubey | D5: =G5/30*10000 -> 8666.6667 | E5: Office | F5: 46027 | G5: =_xlfn.DAYS(H5,F5) -> 26 | H5: 46053
A6: =A5+1 -> 4 | B6: Mobile | C6: Aditya | D6: 0 | E6: Office
A7: =A6+1 -> 5 | B7: Mobile | C7: Anoop | D7: =G7/30*15000 -> 7500 | E7: Office | F7: 46038 | G7: =_xlfn.DAYS(H7,F7) -> 15 | H7: 46053
A8: =A7+1 -> 6 | B8: HR | C8: Prachi Lohani | D8: 25000 | E8: Office
A9: =A8+1 -> 7 | B9: Sales | C9: Ishika Rawal | D9: 0 | E9: Office
A10: =A9+1 -> 8 | B10: Sales | C10: Resource 2 | E10: Office
A11: =A10+1 -> 9 | B11: Sales | C11: Haider | D11: 37500 | E11: Office
A12: =A11+1 -> 10 | B12: Testing | C12: Resource 3 | E12: Office
A13: =A12+1 -> 11 | B13: Web - Back end | C13: Priyanka | D13: 30000 | E13: Office
A14: =A13+1 -> 12 | B14: Web - Back end | C14: Dev kumar Sharma | D14: 40000 | E14: WFH
C17: Total Salary | D17: =SUM(D3:D15) -> 172833.33
C18: Office rent | D18: 32000
C19: Misc | D19: 18000
C20: Marketing | D20: 180000
C21: IT subscriptions | D21: 4000
C24: Total Monthly Expenses | D24: =SUM(D17:D21) -> 406833.33
C25: Annual Expenses | D25: =D24*12 -> 4882000
C26: Per partner Expenses | D26: =D24/4 -> 101708.33

Sheet Income(International)
A1: Sno | B1: Day | C1: Date | D1: Project | E1: Sale | F1: Currency | G1: Mode | H1: Project | I1: Client Name | J1: Country

Sheet Income
A1: Sno | B1: Day | C1: Date | D1: Type of Sale | E1: Project Type | F1: Resource | G1: Project Name | H1: Client Name | I1: Country | J1: State | K1: Sale | L1: Currency | M1: Income Receiver | N1: Mode | P1: Row Labels | Q1: Sum of Sale
A2: 1 | B2: =TEXT(C2,"dddd") -> Monday | C2: 45908 | D2: New Acquisition | E2: Android+IOS App | F2: N/A | G2: Employee India | H2: Taufeeq | I2: India | J2: Uttar Pradesh | K2: 25000 | L2: 1 | M2: Chandan | N2: Axis Bank UPI | P2: Parul Sandilya | Q2: 658500
A3: =A2+1 -> 2 | B3: =TEXT(C3,"dddd") -> Tuesday | C3: 45916 | D3: New Acquisition | E3: Android App | F3: Prachi Lohani | G3: Makroo | H3: Umar | I3: India | J3: Jammu | K3: 30000 | L3: 1 | M3: Account-ArgosMob | N3: PhonePe | P3: Prachi Lohani | Q3: 640001
A4: =A3+1 -> 3 | B4: =TEXT(C4,"dddd") -> Sunday | C4: 45921 | D4: New Acquisition | E4: AI | F4: Parul Sandilya | G4: AI | H4: Sushil | I4: India | J4: Uttar Pradesh | K4: 20000 | L4: 1 | M4: Chandan | N4: Axis Bank UPI | P4: Haider | Q4: 530500
A5: =A4+1 -> 4 | B5: =TEXT(C5,"dddd") -> Friday | C5: 45926 | D5: New Acquisition | E5: Website | F5: N/A | G5: Healthy Manushya | H5: Arun Sharma | I5: India | J5: Punjab | K5: 10000 | L5: 1 | M5: Account-ArgosMob | N5: Net Banking | P5: N/A | Q5: 321837.42
A6: =A5+1 -> 5 | B6: =TEXT(C6,"dddd") -> Wednesday | C6: 45931 | D6: New Acquisition | E6: Android+IOS App+Website | F6: Prachi Lohani | G6: MediConnect | H6: Brij | I6: India | J6: Haryana | K6: 99000 | L6: 1 | M6: Account-ArgosMob | N6: UPI | P6: Grand Total | Q6: 2150838.4
A7: =A6+1 -> 6 | B7: =TEXT(C7,"dddd") -> Thursday | C7: 45932 | D7: New Acquisition | E7: Android+IOS App+Website | F7: Prachi Lohani | G7: MediConnect | H7: Brij | I7: India | J7: Haryana | K7: 81000 | L7: 1 | M7: Account-ArgosMob | N7: UPI
A8: =A7+1 -> 7 | B8: =TEXT(C8,"dddd") -> Friday | C8: 45933 | D8: Old Acquisition | E8: Android App | F8: Prachi Lohani | G8: Makroo | H8: Umar | I8: India | J8: Jammu | K8: 30000 | L8: 1 | M8: Account-ArgosMob | N8: PhonePe
A9: =A8+1 -> 8 | B9: =TEXT(C9,"dddd") -> Friday | C9: 45940 | D9: New Acquisition | E9: Android+IOS App | F9: Prachi Lohani | G9: Fornix | H9: Venket | I9: India | J9: Karnataka | K9: 40000 | L9: 1 | M9: Account-ArgosMob | N9: UPI
A10: =A9+1 -> 9 | B10: =TEXT(C10,"dddd") -> Monday | C10: 45943 | D10: Old Acquisition | E10: Android+IOS App | F10: N/A | G10: Employee India | H10: Taufeeq | I10: India | J10: Uttar Pradesh | K10: 25000 | L10: 1 | M10: Cash | N10: Cash
A11: =A10+1 -> 10 | B11: =TEXT(C11,"dddd") -> Tuesday | C11: 45944 | D11: New Acquisition | E11: AI | F11: N/A | G11: Stenna | H11: Madhur Goel | I11: India | J11: Delhi | K11: 20000 | L11: 1 | M11: Account-ArgosMob | N11: Net Banking
A12: =A11+1 -> 11 | B12: =TEXT(C12,"dddd") -> Thursday | C12: 45946 | D12: New Acquisition | E12: Android+IOS App | F12: Parul Sandilya | G12: Bla-Bla | H12: Prem Reddy | I12: India | J12: Karnataka | K12: 15000 | L12: 1 | M12: Account-ArgosMob | N12: UPI
A13: =A12+1 -> 12 | B13: =TEXT(C13,"dddd") -> Friday | C13: 45947 | D13: New Acquisition | E13: Android+IOS App | F13: Parul Sandilya | G13: Bhardwaj hospital | H13: Dr Arun | I13: India | J13: Uttar Pradesh | K13: 22500 | L13: 1 | M13: Account-ArgosMob | N13: UPI
A14: =A13+1 -> 13 | B14: =TEXT(C14,"dddd") -> Friday | C14: 45947 | D14: New Acquisition | E14: Android+IOS App | F14: Parul Sandilya | G14: Eco Volt Solar | H14: Kuldeep | I14: India | J14: Uttar Pradesh | K14: 40000 | L14: 1 | M14: Account-ArgosMob | N14: Net Banking
A15: =A14+1 -> 14 | B15: =TEXT(C15,"dddd") -> Friday | C15: 45954 | D15: Old Acquisition | E15: AI | F15: Parul Sandilya | G15: AI | H15: Sushil | I15: India | J15: Uttar Pradesh | K15: 20000 | L15: 1 | M15: Chandan | N15: Axis Bank UPI
A16: =A15+1 -> 15 | B16: =TEXT(C16,"dddd") -> Wednesday | C16: 45959 | D16: New Acquisition | E16: Website | F16: N/A | G16: Makroo | H16: Umar | I16: India | J16: Jammu | K16: 5000 | L16: 1 | M16: Account-ArgosMob | N16: PhonePe
A17: =A16+1 -> 16 | B17: =TEXT(C17,"dddd") -> Monday | C17: 45964 | D17: New Acquisition | E17: Android+IOS App | F17: Parul Sandilya | G17: Soya Products-Ecom | H17: M M Mishra | I17: India | J17: Uttar Pradesh | K17: 11000 | L17: 1 | M17: Account-ArgosMob | N17: Net Banking
A18: =A17+1 -> 17 | B18: =TEXT(C18,"dddd") -> Friday | C18: 45968 | D18: Old Acquisition | E18: Android+IOS App+Website | F18: Prachi Lohani | G18: MediConnect | H18: Brij | I18: India | J18: Haryana | K18: 1 | L18: 1 | M18: Account-ArgosMob | N18: UPI
... A32: =A31+1 -> 31 | B32: =TEXT(C32,"dddd") -> Monday | C32: 45985 | D32: New Acquisition | E32: Android+IOS App | F32: Haider | G32: SK Car Finance | H32: Prateek Srivastava | I32: India | J32: Uttar Pradesh | K32: 10000 | L32: 1 | M32: Account-ArgosMob | N32: Axis Bank UPI
A33: =A32+1 -> 32 | B33: =TEXT(C33,"dddd") -> Tuesday | C33: 45986 | D33: New Acquisition | E33: Android+IOS App | F33: N/A | G33: NGK | H33: Strini Naidu | I33: South Africa | K33: 52337.42 | L33: 1 | M33: Chandan | N33: Net Banking
A34: =A33+1 -> 33 | B34: =TEXT(C34,"dddd") -> Thursday | C34: 45988 | D34: New Acquisition | E34: Android+IOS App+Website | F34: Parul Sandilya | G34: Local Market Online | H34: Vinod Khosla | I34: India | J34: Punjab | K34: 80000 | L34: 1 | M34: Account-ArgosMob | N34: Net Banking
A35: =A34+1 -> 34 | B35: =TEXT(C35,"dddd") -> Saturday | C35: 45990 | D35: New Acquisition | E35: Android+IOS App | F35: Haider | G35: School Management App | H35: Amitosh Chaudhary | I35: India | J35: Bihar | K35: 65000 | L35: 1 | M35: Account-ArgosMob | N35: Net Banking
A36: =A35+1 -> 35 | B36: =TEXT(C36,"dddd") -> Monday | C36: 45992 | D36: New Acquisition | E36: Android App | F36: Parul Sandilya | G36: Real estate Data Management | H36: Akash Tripathi | I36: India | J36: Lucknow | K36: 32000 | L36: 1 | M36: Chandan | N36: Gateway
A37: =A36+1 -> 36 | B37: =TEXT(C37,"dddd") -> Tuesday | C37: 45993 | D37: New Acquisition | E37: Android+IOS App+Website | F37: Parul Sandilya | G37: Agriebookhub | H37: Sanjay Kumar | I37: India | J37: Madhya Pradesh | K37: 40000 | L37: 1 | M37: Chandan | N37: Gateway
A38: =A37+1 -> 37 | B38: =TEXT(C38,"dddd") -> Friday | C38: 45996 | D38: New Acquisition | E38: Android+IOS App | F38: Haider | G38: Digital Poster App | H38: Gaurav Shashti | I38: India | J38: Maharashtra | K38: 35000 | L38: 1 | M38: Account-ArgosMob | N38: Net Banking
A39: =A38+1 -> 38 | B39: =TEXT(C39,"dddd") -> Friday | C39: 45996 | D39: Old Acquisition | E39: Android+IOS App | F39: Parul Sandilya | G39: Bla-Bla | H39: Prem Reddy | I39: India | J39: Karnataka | K39: 34000 | L39: 1 | M39: Account-ArgosMob | N39: UPI
A40: =A39+1 -> 39 | B40: =TEXT(C40,"dddd") -> Monday | C40: 45999 | D40: Old Acquisition | E40: Android+IOS App | F40: Haider | G40: Easy Rasta | H40: Dennis Anthony | I40: India | J40: Karnataka | K40: 45000 | L40: 1 | M40: Account-ArgosMob | N40: PhonePe
A41: =A40+1 -> 40 | B41: =TEXT(C41,"dddd") -> Tuesday | C41: 46000 | D41: Old Acquisition | E41: Android+IOS App | F41: Parul Sandilya | G41: FitLeap | H41: Babu Raj | I41: India | J41: West Bengal | K41: 40000 | L41: 1 | M41: Account-ArgosMob | N41: UPI
A42: =A41+1 -> 41 | B42: =TEXT(C42,"dddd") -> Thursday | C42: 46002 | D42: Old Acquisition | E42: Website | F42: N/A | G42: Healthy Manushya | H42: Arun Sharma | I42: India | J42: Punjab | K42: 10000 | L42: 1 | M42: Account-ArgosMob | N42: UPI
A43: =A42+1 -> 42 | B43: =TEXT(C43,"dddd") -> Thursday | C43: 46002 | D43: New Acquisition | E43: Android+IOS App | F43: Haider | G43: Engineered Hybrid Ride-Sharing Platform | H43: Srishylam Jadi | I43: India | J43: Karnataka | K43: 16500 | L43: 1 | M43: Account-ArgosMob | N43: Net Banking
A44: =A43+1 -> 43 | B44: =TEXT(C44,"dddd") -> Monday | C44: 46006 | D44: New Acquisition | E44: Android+IOS App | F44: Parul Sandilya | G44: OTT App | H44: VanLal | I44: India | J44: Mizoram | K44: 50000 | L44: 1 | M44: Account-ArgosMob | N44: Net Banking
A45: =A44+1 -> 44 | B45: =TEXT(C45,"dddd") -> Tuesday | C45: 46007 | D45: Old Acquisition | E45: Android+IOS App | F45: Parul Sandilya | G45: Eco Volt Solar | H45: Kuldeep | I45: India | J45: Uttar Pradesh | K45: 30000 | L45: 1 | M45: Account-ArgosMob | N45: Net Banking
... A58: =A57+1 -> 57 | B58: =TEXT(C58,"dddd") -> Tuesday | C58: 46042 | D58: New Acquisition | E58: Android+IOS App | F58: Haider | G58: Urban Elite | H58: Mahendra | I58: India | J58: Andaman | K58: 10000 | L58: 1 | M58: Account-ArgosMob | N58: Net Banking
A59: =A58+1 -> 58 | B59: =TEXT(C59,"dddd") -> Saturday | C59: 46046 | E59: Android+IOS App | F59: N/A | G59: Degree India | H59: Taufeeq | I59: India | J59: Uttar Pradesh | K59: 15000 | L59: 1 | M59: Chandan | N59: UPI
A60: =A59+1 -> 59 | B60: =TEXT(C60,"dddd") -> Tuesday | C60: 46049 | D60: Old Acquisition | E60: Android+IOS App | F60: Prachi Lohani | G60: Fornix | H60: Venket | I60: India | J60: Karnataka | K60: 40000 | L60: 1 | M60: Rishabh | N60: UPI
A61: =A60+1 -> 60 | B61: =TEXT(C61,"dddd") -> Tuesday | C61: 46049 | D61: Old Acquisition | E61: Website | F61: N/A | G61: Fornix-website | H61: Venket | I61: India | J61: Karnataka | K61: 10000 | L61: 1 | M61: Rishabh | N61: UPI
A62: =A61+1 -> 61 | B62: =TEXT(C62,"dddd") -> Monday | C62: 46055 | D62: Old Acquisition | E62: Android+IOS App+Website | F62: N/A | G62: Local Market Online-AI work | H62: Vinod Khosla | I62: India | J62: Punjab | K62: 25000 | L62: 1 | M62: Account-KiloWatt | N62: Net Banking
A63: =A62+1 -> 62 | B63: =TEXT(C63,"dddd") -> Monday | C63: 46055 | E63: Android+IOS App+Website | F63: N/A | G63: AI LMS Portal | H63: Arun Swamy | I63: India | J63: Rajasthan | K63: 50000 | L63: 1 | M63: Account-KiloWatt | N63: Net Banking
A64: =A63+1 -> 63 | B64: =TEXT(C64,"dddd") -> Friday | C64: 46059 | E64: Website | F64: N/A | G64: Stenna-website | H64: Madhur Goel | I64: India | J64: Delhi | K64: 25000 | L64: 1 | M64: Account-KiloWatt | N64: UPI
A65: =A64+1 -> 64 | B65: =TEXT(C65,"dddd") -> Saturday | C65: 46060 | D65: New Acquisition | E65: Android+IOS App | F65: Haider | G65: Urban Elite | H65: Mahendra | I65: India | J65: Andaman | K65: 30000 | L65: 1 | M65: Account-KiloWatt | N65: Net Banking
A66: =A65+1 -> 65 | B66: =TEXT(C66,"dddd") -> Tuesday | C66: 46063 | D66: New Acquisition | E66: Android+IOS App | F66: N/A | G66: NGK | H66: Strini Naidu | I66: South Africa | K66: 89773.9 | L66: 1 | M66: Chandan | N66: Net Banking
A67: =A66+1 -> 66 | B67: =TEXT(C67,"dddd") -> Wednesday | C67: 46064 | D67: Old Acquisition | E67: Android+IOS App | F67: Parul Sandilya | G67: FitLeap | H67: Babu Raj | I67: India | J67: West Bengal | K67: 40000 | L67: 1 | M67: Account-KiloWatt | N67: UPI
A68: =A67+1 -> 67 | B68: =TEXT(C68,"dddd") -> Friday | C68: 46066 | E68: Android+IOS App+Website | F68: N/A | G68: AI LMS Portal | H68: Arun Swamy | I68: India | J68: Rajasthan | K68: 50000 | L68: 1 | M68: Rishabh | N68: Net Banking
A69: =A68+1 -> 68 | B69: =TEXT(C69,"dddd") -> Friday | C69: 46066 | D69: New Acquisition | E69: Android App | F69: N/A | G69: Real estate Data Management | H69: Akash Tripathi | I69: India | J69: Lucknow | K69: 24000 | L69: 1 | M69: Chandan | N69: Gateway
A70: =A69+1 -> 69 | B70: =TEXT(C70,"dddd") -> Saturday | C70: 46074 | D70: New Acquisition | E70: Website | F70: N/A | G70: Fornix-website | H70: Venket | I70: India | J70: Karnataka | K70: 50000 | L70: 1 | M70: Rishabh | N70: UPI
A71: =A70+1 -> 70 | B71: =TEXT(C71,"dddd") -> Saturday | C71: 46074 | D71: New Acquisition | E71: Android+IOS App+Website | F71: N/A | G71: MediConnect | H71: Brij | I71: India | J71: Haryana | K71: 1 | L71: 1 | M71: Account-KiloWatt | N71: Net Banking
A72: =A71+1 -> 71 | B72: =TEXT(C72,"dddd") -> Saturday | C72: 46074 | D72: New Acquisition | E72: Android+IOS App+Website | F72: N/A | G72: Beingpetz | H72: Mahesh | I72: India | J72: Haryana | K72: 10 | L72: 1 | M72: Account-KiloWatt | N72: Net Banking
A73: =A72+1 -> 72 | B73: =TEXT(C73,"dddd") -> Saturday | C73: 46074 | D73: New Acquisition | E73: Android+IOS App+Website | F73: N/A | G73: MediConnect | H73: Brij | I73: India | J73: Haryana | K73: 49999 | L73: 1 | M73: Account-KiloWatt | N73: Net Banking
A74: =A73+1 -> 73 | B74: =TEXT(C74,"dddd") -> Saturday | C74: 46074 | D74: New Acquisition | E74: Android+IOS App+Website | F74: N/A | G74: Beingpetz | H74: Mahesh | I74: India | J74: Haryana | K74: 15000 | L74: 1 | M74: Account-KiloWatt | N74: Net Banking
A75: =A74+1 -> 74 | B75: =TEXT(C75,"dddd") -> Sunday | C75: 46075 | E75: Android+IOS App+Website | F75: N/A | G75: MediConnect | H75: Brij | I75: India | J75: Haryana | K75: 50000 | L75: 1 | M75: Account-KiloWatt | N75: Net Banking
A76: =A75+1 -> 75 | B76: =TEXT(C76,"dddd") -> Monday | C76: 46076 | E76: Android+IOS App+Website | F76: Haider | G76: Farm produce selling app | H76: Sadiq | I76: India | J76: Uttar Pradesh | K76: 57000 | L76: 1 | M76: Account-ArgosMob | N76: Net Banking
A77: =A76+1 -> 76 | B77: =TEXT(C77,"dddd") -> Wednesday | C77: 46078 | D77: New Acquisition | E77: AI | F77: N/A | G77: AI-maintenance | H77: Sushil | I77: India | J77: Uttar Pradesh | K77: 8000 | L77: 1 | M77: Chandan | N77: Axis Bank UPI
A78: =A77+1 -> 77 | B78: =TEXT(C78,"dddd") -> Saturday | C78: 46081 | E78: Android+IOS App | F78: Akansha | G78: Zippy Equestrian Center | H78: Dilip | I78: India | J78: Karnataka | K78: 82600 | L78: 1 | M78: Account-ArgosMob | N78: Axis Bank UPI
A79: =A78+1 -> 78 | B79: =TEXT(C79,"dddd") -> Monday | C79: 46083 | E79: Android+IOS App+Website | F79: N/A | G79: AI LMS Portal | H79: Arun Swamy | I79: India | J79: Rajasthan | K79: 50000 | L79: 1 | M79: Rishabh | N79: Net Banking
A80: =A79+1 -> 79 | B80: =TEXT(C80,"dddd") -> Monday | C80: 46083 | E80: Website | F80: N/A | G80: Stenna-website | H80: Madhur Goel | I80: India | J80: Delhi | K80: 25000 | L80: 1 | M80: Account-KiloWatt | N80: Net Banking
A81: =A80+1 -> 80 | B81: =TEXT(C81,"dddd") -> Thursday | C81: 46086 | D81: New Acquisition | E81: Android+IOS App | F81: N/A | G81: Beingpetz - Phase 2 | H81: Mahesh | I81: India | J81: Haryana | K81: 30000 | L81: 1 | M81: Account-KiloWatt | N81: Net Banking

Sheet Expenses
A1: Sno | B1: Day | C1: Date | D1: Category | E1: Sub-Category | F1: Line Item | G1: Amount | H1: Paid by | I1: Column1 | J1: Person | K1: Income | L1: Expenses | M1: Net | N1: Income(post 28th Jan26) | O1: Expenses( 28th Jan26) | P1: Net | Q1: Account Settlement | S1: Sno | T1: Component | U1: Amount
A2: 1 | B2: 45901 | C2: =TEXT(B2,"dddd") -> Monday | D2: Marketing | E2: FB Ads | F2: FB Budget : 265425466458147 | G2: 1000 | H2: Chandan | J2: Chandan | K2: =SUMIFS(Income!$K:$K,Income!M:M,Expenses!J2,Income!$C:$C,"<="&Validations!$N$1) -> 261337.42 | L2: =SUMIFS(G:G,H:H,J2,B:B,"<="&Validations!$N$1) -> 130143.43 | M2: =K2-L2 -> 131193.99 | N2: =SUMIFS(Income!$K:$K,Income!$M:$M,Expenses!J2,Income!$C:$C,">="&Validations!$N$1) -> 121773.9 | O2: =SUMIFS($G:$G,Expenses!$B:$B,">="&Validations!$N$1,Expenses!$H:$H,Expenses!J2,D:D,"<>"&"Salary") -> 90891.9 | P2: =N2-O2 -> 30882 | Q2: =($L$13+SUM($P$2:$P$5)+$P$9)/5-P2 -> 62565.606 | S2: 1 | T2: Equity | U2: =SUMIFS(G:G,H:H,J9,D:D,T2) -> 433683.33
A3: =A2+1 -> 2 | B3: 45901 | C3: =TEXT(B3,"dddd") -> Monday | D3: Office expense | E3: Chai/Coffee | G3: 80 | H3: Rishabh | J3: Krishna | K3: =SUMIFS(Income!$K:$K,Income!M:M,Expenses!J3,Income!$C:$C,"<="&Validations!$N$1) -> 0 | L3: =SUMIFS(G:G,H:H,J3,B:B,"<="&Validations!$N$1) -> -125530.99 | M3: =K3-L3 -> 125530.99 | N3: =SUMIFS(Income!$K:$K,Income!$M:$M,Expenses!J3,Income!$C:$C,">="&Validations!$N$1) -> 0 | O3: =SUMIFS($G:$G,Expenses!$B:$B,">="&Validations!$N$1,Expenses!$H:$H,Expenses!J3,D:D,"<>"&"Salary") -> -44061.18 | P3: =N3-O3 -> 44061.18 | Q3: =($L$13+SUM($P$2:$P$5)+$P$9)/5-P3 -> 49386.426 | S3: 2 | T3: Loan | U3: =SUMIFS(G:G,H:H,J9,D:D,T3) -> 166816.67
A4: =A3+1 -> 3 | B4: 45901 | C4: =TEXT(B4,"dddd") -> Monday | D4: Office expense | G4: 100 | H4: Rishabh | J4: Rishabh | K4: =SUMIFS(Income!$K:$K,Income!M:M,Expenses!J4,Income!$C:$C,"<="&Validations!$N$1) -> 50000 | L4: =SUMIFS(G:G,H:H,J4,B:B,"<="&Validations!$N$1) -> -75398.993 | M4: =K4-L4 -> 125398.99 | N4: =SUMIFS(Income!$K:$K,Income!$M:$M,Expenses!J4,Income!$C:$C,">="&Validations!$N$1) -> 150000 | O4: =SUMIFS($G:$G,Expenses!$B:$B,">="&Validations!$N$1,Expenses!$H:$H,Expenses!J4,D:D,"<>"&"Salary") -> 101848.02 | P4: =N4-O4 -> 48151.98 | Q4: =($L$13+SUM($P$2:$P$5)+$P$9)/5-P4 -> 45295.626
A5: =A4+1 -> 4 | B5: 45901 | C5: =TEXT(B5,"dddd") -> Monday | D5: Food | G5: 252 | H5: Krishna | J5: Vansh | K5: =SUMIFS(Income!$K:$K,Income!M:M,Expenses!J5,Income!$C:$C,"<="&Validations!$N$1) -> 45000 | L5: =SUMIFS(G:G,H:H,J5,B:B,"<="&Validations!$N$1) -> -80053.993 | M5: =K5-L5 -> 125053.99 | N5: =SUMIFS(Income!$K:$K,Income!$M:$M,Expenses!J5,Income!$C:$C,">="&Validations!$N$1) -> 0 | O5: =SUMIFS($G:$G,Expenses!$B:$B,">="&Validations!$N$1,Expenses!$H:$H,Expenses!J5,D:D,"<>"&"Salary") -> -31058 | P5: =N5-O5 -> 31058 | Q5: =($L$13+SUM($P$2:$P$5)+$P$9)/5-P5 -> 62389.606 | T5: Total | U5: =SUM(U2:U3) -> 600500
A6: =A5+1 -> 5 | B6: 45902 | C6: =TEXT(B6,"dddd") -> Tuesday | D6: Office expense | E6: Chai/Coffee | G6: 215 | H6: Rishabh | J6: Account-ArgosMob | K6: =SUMIFS(Income!$K:$K,Income!M:M,Expenses!J6,Income!$C:$C,"<="&Validations!$N$1) -> 1639501 | L6: =SUMIFS(G:G,H:H,J6,B:B,"<="&Validations!$N$1) -> 1639501 | M6: =K6-L6 -> 0 | N6: =SUMIFS(Income!$K:$K,Income!$M:$M,Expenses!J6,Income!$C:$C,">="&Validations!$N$1) -> 139600 | O6: =SUMIFS($G:$G,Expenses!$B:$B,">="&Validations!$N$1,Expenses!$H:$H,Expenses!J6,D:D,"<>"&"Salary") -> 4051.93 | P6: =N6-O6 -> 135548.07 | T6: Deficit/Surplus | U6: =L13-U5 -> -302944.13
A7: =A6+1 -> 6 | B7: 45902 | C7: =TEXT(B7,"dddd") -> Tuesday | D7: Electricity Recharge | E7: TS-618 | F7: TS-618 | G7: 2500 | H7: Rishabh | J7: Account-KiloWatt | K7: =SUMIFS(Income!$K:$K,Income!M:M,Expenses!J7,Income!$C:$C,"<="&Validations!$N$1) -> 0 | L7: =SUMIFS(G:G,H:H,J7,B:B,"<="&Validations!$N$1) -> 4.5297099e-14 | M7: =K7-L7 -> -4.5297099e-14 | N7: =SUMIFS(Income!$K:$K,Income!$M:$M,Expenses!J7,Income!$C:$C,">="&Validations!$N$1) -> 340010 | O7: =SUMIFS($G:$G,Expenses!$B:$B,">="&Validations!$N$1,Expenses!$H:$H,Expenses!J7) -> 200268.2 | P7: =N7-O7 -> 139741.8
A8: =A7+1 -> 7 | B8: 45902 | C8: =TEXT(B8,"dddd") -> Tuesday | D8: Marketing | E8: FB Ads | F8: FB Budget : 265425466458147 | G8: 20000 | H8: Chandan | J8: Cash | K8: =SUMIFS(Income!$K:$K,Income!M:M,Expenses!J8,Income!$C:$C,"<="&Validations!$N$1) -> 25000 | L8: =SUMIFS(G:G,H:H,J8,B:B,"<="&Validations!$N$1) -> 25000 | M8: =K8-L8 -> 0 | N8: =SUMIFS(Income!$K:$K,Income!$M:$M,Expenses!J8,Income!$C:$C,">="&Validations!$N$1) -> 0 | O8: =SUMIFS($G:$G,Expenses!$B:$B,">="&Validations!$N$1,Expenses!$H:$H,Expenses!J8) -> -22266 | P8: =N8-O8 -> 22266
A9: =A8+1 -> 8 | B9: 45902 | C9: =TEXT(B9,"dddd") -> Tuesday | D9: Office expense | E9: Maggi/Tea | G9: 428 | H9: Rishabh | J9: Dr Chadha | K9: =SUMIFS(Income!$K:$K,Income!M:M,Expenses!J9,Income!$C:$C,"<="&Validations!$N$1) -> 0 | L9: =SUMIFS(G:G,H:H,J9,B:B,"<="&Validations!$N$1) -> 0 | M9: =K9-L9 -> 0 | N9: =SUMIFS(Income!$K:$K,Income!$M:$M,Expenses!J9,Income!$C:$C,">="&Validations!$N$1) -> 0 | O9: =SUMIFS($G:$G,Expenses!$B:$B,">="&Validations!$N$1,Expenses!$H:$H,Expenses!J9,D:D,"<>"&"Loan",D:D,"<>"&"equity") -> -15529 | P9: =N9-O9 -> 15529 | Q9: =($L$13+SUM($P$2:$P$5)+$P$9)/5-P9 -> 77918.606
A10: =A9+1 -> 9 | B10: 45903 | C10: =TEXT(B10,"dddd") -> Wednesday | D10: Dialer recharge | G10: 500 | H10: Krishna | J10: Jitendra ji | K10: =SUMIFS(Income!$K:$K,Income!M:M,Expenses!J10,Income!$C:$C,"<="&Validations!$N$1) -> 0 | L10: =SUMIF(H:H,J10,G:G) -> -15529 | M10: =K10-L10 -> 15529
A11: =A10+1 -> 10 | B11: 45903 | C11: =TEXT(B11,"dddd") -> Wednesday | D11: Office expense | E11: Chai | G11: 30 | H11: Rishabh
A12: =A11+1 -> 11 | B12: 45903 | C12: =TEXT(B12,"dddd") -> Wednesday | D12: Office expense | F12: Printout | G12: 64 | H12: Chandan
A13: =A12+1 -> 12 | B13: 45903 | C13: =TEXT(B13,"dddd") -> Wednesday | D13: Office expense | E13: Coffee Sachets | G13: 96 | H13: Vansh | K13: Cash IN Hand | L13: =SUM(P6:P8) -> 297555.87
A14: =A13+1 -> 13 | B14: 45904 | C14: =TEXT(B14,"dddd") -> Thursday | D14: Office expense | E14: Prachi B'day Cake | G14: 685 | H14: Rishabh
A15: =A14+1 -> 14 | B15: 45905 | C15: =TEXT(B15,"dddd") -> Friday | D15: Office expense | E15: Fun | G15: 191 | H15: Krishna
A16: =A15+1 -> 15 | B16: 45908 | C16: =TEXT(B16,"dddd") -> Monday | D16: Office expense | E16: Tea | G16: 40 | H16: Rishabh
A17: =A16+1 -> 16 | B17: 45908 | C17: =TEXT(B17,"dddd") -> Monday | D17: Office expense | E17: Mouse | G17: 619 | H17: Krishna
A18: =A17+1 -> 17 | B18: 45909 | C18: =TEXT(B18,"dddd") -> Tuesday | D18: Office expense | E18: Chai/Coffee | G18: 105 | H18: Krishna | J18: Row Labels | K18: Sum of Amount
A19: =A18+1 -> 18 | B19: 45909 | C19: =TEXT(B19,"dddd") -> Tuesday | D19: Office expense | E19: Lunch | G19: 1134 | H19: Krishna | J19: Client Expenses | K19: 26070.76
A20: =A19+1 -> 19 | B20: 45909 | C20: =TEXT(B20,"dddd") -> Tuesday | D20: Office expense | E20: Coke lunch | G20: 140 | H20: Krishna | J20: Company Expense | K20: 2475
A21: =A20+1 -> 20 | B21: 45909 | C21: =TEXT(B21,"dddd") -> Tuesday | D21: Office expense | E21: Chai/Coffee | G21: 179 | H21: Vansh | J21: Dialer recharge | K21: 500
A22: =A21+1 -> 21 | B22: 45909 | C22: =TEXT(B22,"dddd") -> Tuesday | D22: Office expense | E22: Stationary | G22: 120 | H22: Krishna | J22: Electricity Recharge | K22: 5500
A23: =A22+1 -> 22 | B23: 45910 | C23: =TEXT(B23,"dddd") -> Wednesday | D23: Office expense | E23: Chai/Coffee | G23: 165 | H23: Krishna | J23: Fixed Expense | K23: 97653.98
A24: =A23+1 -> 23 | B24: 45910 | C24: =TEXT(B24,"dddd") -> Wednesday | D24: Salary | E24: Previous staff salary | F24: Paid to Aradhna | G24: 3000 | H24: Account-ArgosMob | J24: Food | K24: 5024.98
A25: =A24+1 -> 24 | B25: 45911 | C25: =TEXT(B25,"dddd") -> Thursday | D25: Office expense | E25: Chai/Coffee | G25: 120 | H25: Krishna | J25: Fun | K25: 180756.13
A26: =A25+1 -> 25 | B26: 45912 | C26: =TEXT(B26,"dddd") -> Friday | D26: Office expense | E26: Basket, colin, vim bar | G26: 385 | H26: Krishna | J26: Marketing | K26: 280500
A27: =A26+1 -> 26 | B27: 45915 | C27: =TEXT(B27,"dddd") -> Monday | D27: Office expense | E27: Chai/Coffee | G27: 165 | H27: Chandan | J27: Office expense | K27: 227225.39
A28: =A27+1 -> 27 | B28: 45916 | C28: =TEXT(B28,"dddd") -> Tuesday | D28: Office expense | E28: Mobile recharge | G28: 542 | H28: Krishna | J28: Operating Expenses | K28: 15000
A29: =A28+1 -> 28 | B29: 45916 | C29: =TEXT(B29,"dddd") -> Tuesday | D29: Office expense | E29: Chai/Coffee | G29: 545 | H29: Krishna | J29: Outsouce | K29: 5000
A30: =A29+1 -> 29 | B30: 45917 | C30: =TEXT(B30,"dddd") -> Wednesday | D30: Office expense | E30: Chai/Coffee | G30: 260 | H30: Vansh | J30: Salary | K30: 1424908.2
A31: =A30+1 -> 30 | B31: 45917 | C31: =TEXT(B31,"dddd") -> Wednesday | D31: Office expense | E31: KFC | G31: 667 | H31: Vansh | J31: Self Withdrawl | K31: -20187.6
A32: =A31+1 -> 31 | B32: 45918 | C32: =TEXT(B32,"dddd") -> Thursday | D32: Office expense | E32: Chai/Coffee | G32: 280 | H32: Krishna | J32: Grand Total | K32: 2250426.9
A33: =A32+1 -> 32 | B33: 45918 | C33: =TEXT(B33,"dddd") -> Thursday | D33: Office expense | E33: Electricity | G33: 1000 | H33: Krishna
A34: =A33+1 -> 33 | B34: 45918 | C34: =TEXT(B34,"dddd") -> Thursday | D34: Office expense | E34: Ice cream | G34: 260 | H34: Krishna
A35: =A34+1 -> 34 | B35: 45918 | C35: =TEXT(B35,"dddd") -> Thursday | D35: Office expense | E35: Internet | G35: 1005 | H35: Vansh
A36: =A35+1 -> 35 | B36: 45920 | C36: =TEXT(B36,"dddd") -> Saturday | D36: Bank Expenses | F36: Non-maintenance of AQB | G36: 1623.97 | H36: Account-ArgosMob
A37: =A36+1 -> 36 | B37: 45921 | C37: =TEXT(B37,"dddd") -> Sunday | D37: Fixed Expense | F37: Office 365: 2240920005 | G37: 179.66 | H37: Account-ArgosMob
A38: =A37+1 -> 37 | B38: 45922 | C38: =TEXT(B38,"dddd") -> Monday | D38: Office expense | E38: Maid-618 | G38: 1000 | H38: Chandan
A39: =A38+1 -> 38 | B39: 45922 | C39: =TEXT(B39,"dddd") -> Monday | D39: Self Funding | F39: Paid to Argomsob for rent | G39: 20000 | H39: Chandan
A40: =A39+1 -> 39 | B40: 45922 | C40: =TEXT(B40,"dddd") -> Monday | D40: Self Funding | F40: Received from Chandan | G40: -20000 | H40: Account-ArgosMob
A41: =A40+1 -> 40 | B41: 45922 | C41: =TEXT(B41,"dddd") -> Monday | D41: Fixed Expense | E41: Rent | F41: Paid to Alok for rent 618 | G41: 32000 | H41: Account-ArgosMob
A42: =A41+1 -> 41 | B42: 45923 | C42: =TEXT(B42,"dddd") -> Tuesday | D42: Marketing | E42: FB Ads | F42: FB Budget : 265425466458147 | G42: 20000 | H42: Chandan
A43: =A42+1 -> 42 | B43: 45924 | C43: =TEXT(B43,"dddd") -> Wednesday | D43: Office expense | E43: Electricity | F43: Office 618 | G43: 2000 | H43: Chandan
A44: =A43+1 -> 43 | B44: 45924 | C44: =TEXT(B44,"dddd") -> Wednesday | D44: Office expense | E44: Fun | F44: Paid for Pool | G44: 230 | H44: Krishna
A45: =A44+1 -> 44 | B45: 45924 | C45: =TEXT(B45,"dddd") -> Wednesday | D45: Office expense | E45: Faluda | G45: 180 | H45: Rishabh
A46: =A45+1 -> 45 | B46: 45925 | C46: =TEXT(B46,"dddd") -> Thursday | D46: Office expense | E46: Chai/Coffee | G46: 240 | H46: Krishna
A47: =A46+1 -> 46 | B47: 45925 | C47: =TEXT(B47,"dddd") -> Thursday | D47: Office expense | E47: Chai/Coffee | G47: 45 | H47: Rishabh
A48: =A47+1 -> 47 | B48: 45925 | C48: =TEXT(B48,"dddd") -> Thursday | D48: Office expense | E48: Coffee/Lemonade | G48: 480 | H48: Rishabh
A49: =A48+1 -> 48 | B49: 45929 | C49: =TEXT(B49,"dddd") -> Monday | D49: Office expense | E49: Bowling | G49: 1000 | H49: Krishna
A50: =A49+1 -> 49 | B50: 45930 | C50: Tuesday | D50: Office expense | E50: Fun | F50: Paid for Pool | G50: 210 | H50: Krishna
A51: =A50+1 -> 50 | B51: 45931 | C51: =TEXT(B51,"dddd") -> Wednesday | D51: Office expense | F51: Cartridge Refill | G51: 450 | H51: Rishabh
A52: =A51+1 -> 51 | B52: 45931 | C52: =TEXT(B52,"dddd") -> Wednesday | D52: Office expense | F52: Tea | G52: 965 | H52: Rishabh
A53: =A52+1 -> 52 | B53: 45931 | C53: =TEXT(B53,"dddd") -> Wednesday | D53: Fun | F53: Dosa | G53: 480 | H53: Chandan
A54: =A53+1 -> 53 | B54: 45931 | C54: =TEXT(B54,"dddd") -> Wednesday | D54: Fun | F54: Ice cream/Coffee | G54: 320 | H54: Rishabh
A55: =A54+1 -> 54 | B55: 45936 | C55: Monday | D55: Office expense | E55: Fun | F55: Paid for Pool | G55: 238 | H55: Krishna
A56: =A55+1 -> 55 | B56: 45936 | C56: =TEXT(B56,"dddd") -> Monday | D56: Marketing | E56: FB Ads | F56: Paid to Chandan for FB Budget | G56: 20000 | H56: Account-ArgosMob
A57: =A56+1 -> 56 | B57: 45936 | C57: =TEXT(B57,"dddd") -> Monday | D57: Marketing | E57: FB Ads | F57: FB Budget : 265425466458147 | G57: -20000 | H57: Chandan
A58: =A57+1 -> 57 | B58: 45936 | C58: =TEXT(B58,"dddd") -> Monday | D58: Marketing | E58: FB Ads | F58: FB Budget : 265425466458147 | G58: 20000 | H58: Chandan
A59: =A58+1 -> 58 | B59: 45937 | C59: =TEXT(B59,"dddd") -> Tuesday | D59: Operating Expenses | E59: Salary | F59: Self Withdrawl for Salary | G59: -80000 | H59: Vansh
A60: =A59+1 -> 59 | B60: 45937 | C60: =TEXT(B60,"dddd") -> Tuesday | D60: Operating Expenses | E60: Salary | F60: Paid to Vansh for Salary | G60: 80000 | H60: Account-ArgosMob
A61: =A60+1 -> 60 | B61: 45937 | C61: =TEXT(B61,"dddd") -> Tuesday | D61: Operating Expenses | E61: Salary | F61: Self Funding for Salary | G61: 61500 | H61: Vansh
A62: =A61+1 -> 61 | B62: 45937 | C62: =TEXT(B62,"dddd") -> Tuesday | D62: Operating Expenses | E62: Salary | F62: Received from Vansh for Salary | G62: -61500 | H62: Account-KiloWatt
A63: =A62+1 -> 62 | B63: 45937 | C63: =TEXT(B63,"dddd") -> Tuesday | D63: Operating Expenses | E63: Salary | F63: Self Funding for Salary | G63: 18500 | H63: Vansh
A64: =A63+1 -> 63 | B64: 45937 | C64: =TEXT(B64,"dddd") -> Tuesday | D64: Operating Expenses | E64: Salary | F64: Received from Vansh for Salary | G64: -18500 | H64: Account-ArgosMob
A65: =A64+1 -> 64 | B65: 45937 | C65: =TEXT(B65,"dddd") -> Tuesday | D65: Salary | E65: Salary | F65: Sept-25 - Parul | G65: 31500 | H65: Account-KiloWatt
A66: =A65+1 -> 65 | B66: 45937 | C66: =TEXT(B66,"dddd") -> Tuesday | D66: Salary | E66: Salary | F66: Sept-25 - Prachi Lohani | G66: 30000 | H66: Account-KiloWatt
A67: =A66+1 -> 66 | B67: 45937 | C67: =TEXT(B67,"dddd") -> Tuesday | D67: Salary | E67: Salary | F67: Sept-25 - Dev | G67: 40000 | H67: Account-ArgosMob
... A71: =A70+1 -> 70 | B71: 45937 | C71: =TEXT(B71,"dddd") -> Tuesday | D71: Salary | E71: Salary | F71: Sept-25 - Inayat | G71: 20000 | H71: Account-ArgosMob
A72: =A71+1 -> 71 | B72: 45937 | C72: =TEXT(B72,"dddd") -> Tuesday | D72: Self Withdrawl | F72: Self Withdrawl for Electricity | G72: 5000 | H72: Account-ArgosMob
A73: =A72+1 -> 72 | B73: 45937 | C73: =TEXT(B73,"dddd") -> Tuesday | D73: Office expense | F73: Received for Electricity | G73: -5000 | H73: Chandan
A74: =A73+1 -> 73 | B74: 45937 | C74: =TEXT(B74,"dddd") -> Tuesday | D74: Operating Expenses | E74: Electricity | F74: Paid for electricity | G74: 5000 | H74: Chandan
A75: =A74+1 -> 74 | B75: 45937 | C75: =TEXT(B75,"dddd") -> Tuesday | D75: Office expense | E75: Fun | F75: Paid for Pool | G75: 248 | H75: Krishna
A76: =A75+1 -> 75 | B76: 45938 | C76: =TEXT(B76,"dddd") -> Wednesday | D76: Office expense | E76: Maid-1003 | F76: Paid to maid-1003 | G76: 1200 | H76: Chandan
A77: =A76+1 -> 76 | B77: 45940 | C77: =TEXT(B77,"dddd") -> Friday | D77: Office expense | F77: Paid for Diwali Event | G77: 2000 | H77: Account-ArgosMob
A78: =A77+1 -> 77 | B78: 45943 | C78: =TEXT(B78,"dddd") -> Monday | D78: Office expense | F78: Windfall Income | G78: -200 | H78: Krishna
A79: =A78+1 -> 78 | B79: 45943 | C79: =TEXT(B79,"dddd") -> Monday | D79: Office expense | F79: For Lock | G79: 1500 | H79: Cash
A80: =A79+1 -> 79 | B80: 45943 | C80: =TEXT(B80,"dddd") -> Monday | D80: Self withdrawl | F80: Self withdrawal-Vansh | G80: -10000 | H80: Vansh
A81: =A80+1 -> 80 | B81: 45943 | C81: =TEXT(B81,"dddd") -> Monday | D81: Self withdrawl | F81: For self withdrawl | G81: 10000 | H81: Account-ArgosMob
A82: =A81+1 -> 81 | B82: 45943 | C82: =TEXT(B82,"dddd") -> Monday | D82: Office expense | F82: Paid for water | G82: 440 | H82: Chandan
A83: =A82+1 -> 82 | B83: 45943 | C83: =TEXT(B83,"dddd") -> Monday | D83: Office expense | F83: For team evening lunch | G83: 1000 | H83: Cash
A84: =A83+1 -> 83 | B84: 45943 | C84: =TEXT(B84,"dddd") -> Monday | D84: Office expense | E84: Fun | F84: Paid for Pool | G84: 210 | H84: Krishna
A85: =A84+1 -> 84 | B85: 45943 | C85: =TEXT(B85,"dddd") -> Monday | D85: Office expense | F85: For team evening lunch | G85: 100 | H85: Krishna
A86: =A85+1 -> 85 | B86: 45944 | C86: =TEXT(B86,"dddd") -> Tuesday | D86: Operating Expenses | E86: Salary | F86: Sept-25 - Abdulla | G86: 10000 | H86: Account-ArgosMob
A87: =A86+1 -> 86 | B87: 45944 | C87: =TEXT(B87,"dddd") -> Tuesday | D87: Office expense | F87: For Diwali-Dmart | G87: 7500 | H87: Cash
A88: =A87+1 -> 87 | B88: 45944 | C88: =TEXT(B88,"dddd") -> Tuesday | D88: Outsouce | F88: Paid to Anthony | G88: 5000 | H88: Account-ArgosMob
A89: =A88+1 -> 88 | B89: 45944 | C89: =TEXT(B89,"dddd") -> Tuesday | D89: Office expense | F89: Blinkit | G89: 299 | H89: Rishabh
A90: =A89+1 -> 89 | B90: 45945 | C90: =TEXT(B90,"dddd") -> Wednesday | D90: Office expense | F90: For Printer Catridge | G90: 745 | H90: Chandan
A91: =A90+1 -> 90 | B91: 45945 | C91: =TEXT(B91,"dddd") -> Wednesday | D91: Office expense | F91: For Stamp-Parul Client | G91: 160 | H91: Chandan
A92: =A91+1 -> 91 | B92: 45945 | C92: =TEXT(B92,"dddd") -> Wednesday | D92: Fixed Expense | E92: Rent | F92: Paid to Alok for rent 618 | G92: 32000 | H92: Account-ArgosMob
A93: =A92+1 -> 92 | B93: 45945 | C93: =TEXT(B93,"dddd") -> Wednesday | D93: Self Withdrawl | F93: Self Withdrawl for Diwali Purchase | G93: -3000 | H93: Rishabh
A94: =A93+1 -> 93 | B94: 45945 | C94: =TEXT(B94,"dddd") -> Wednesday | D94: Self Withdrawl | F94: Self Withdrawl for Diwali Purchase | G94: 3000 | H94: Account-ArgosMob
A95: =A94+1 -> 94 | B95: 45945 | C95: =TEXT(B95,"dddd") -> Wednesday | D95: Office expense | F95: Paid for Diwali Purchase | G95: 2680 | H95: Rishabh
A96: =A95+1 -> 95 | B96: 45945 | C96: =TEXT(B96,"dddd") -> Wednesday | D96: Fixed Expense | F96: Paid for Mobile-Airtel | G96: 1115 | H96: Rishabh
A97: =A96+1 -> 96 | B97: 45946 | C97: =TEXT(B97,"dddd") -> Thursday | D97: Self Withdrawl | F97: Self Withdrawl for wifi | G97: -2000 | H97: Rishabh
A98: =A97+1 -> 97 | B98: 45946 | C98: =TEXT(B98,"dddd") -> Thursday | D98: Self Withdrawl | F98: Self Withdrawl for wifi | G98: 2000 | H98: Account-ArgosMob
A99: =A98+1 -> 98 | B99: 45946 | C99: =TEXT(B99,"dddd") -> Thursday | D99: Office expense | F99: WIFI Recharge | G99: 1178 | H99: Rishabh
A100: =A99+1 -> 99 | B100: 45946 | C100: =TEXT(B100,"dddd") -> Thursday | D100: Office expense | E100: Team Engagaement | F100: Box Cricket Booking | G100: 500 | H100: Chandan
A101: =A100+1 -> 100 | B101: 45946 | C101: =TEXT(B101,"dddd") -> Thursday | D101: Office expense | F101: Scissor/Tape | G101: 90 | H101: Rishabh
A102: =A101+1 -> 101 | B102: 45946 | C102: =TEXT(B102,"dddd") -> Thursday | D102: Office expense | F102: Lahori Jeera | G102: 261 | H102: Rishabh
A103: =A102+1 -> 102 | B103: 45946 | C103: =TEXT(B103,"dddd") -> Thursday | D103: Office expense | E103: Food | F103: Paid for Food (1 sept to 30th sept) | G103: 1470 | H103: Vansh
...

Sheet Resource Performance
A1: Choose Resource-> | C1: Akansha
A2: 1 | B2: Salary | C2: 33000
A3: 2 | B3: Target(multiple) | C3: 15 | E3: Nov
A4: 3 | B4: Monthly Target | C4: =C3*C2 -> 495000
A5: 4 | B5: Total deal wins | C5: =COUNTIF('Order Book'!E:E,'Resource Performance'!C1) -> 1
A6: 5 | B6: Incentive | C6: 0.02
A9: Date | B9: Month | C9: Year | D9: Contract Wins | E9: Net | F9: Achieved % | G9: Month-On-Month | H9: Incentive
A10: 45901 | B10: =TEXT(DATE(C10,MONTH(A10),DAY(A10)),"MMMM") -> September | C10: 2025 | D10: =SUMIFS('Order Book'!K:K,'Order Book'!E:E,'Resource Performance'!$C$1,'Order Book'!C:C,">="&'Resource Performance'!A10,'Order Book'!C:C,"<="&EOMONTH('Resource Performance'!A10,0)) -> 0 | E10: =SUMIFS(Income!K:K,Income!F:F,'Resource Performance'!$C$1,Income!C:C,">="&'Resource Performance'!A10,Income!C:C,"<="&EOMONTH('Resource Performance'!A10,0)) -> 0 | F10: =D10/$C$4 -> 0 | H10: =IF(D10>=$C$4,$C$6*D10,0) -> 0
A11: =EOMONTH(A10,0)+1 -> 45931 | B11: =TEXT(DATE(C11,MONTH(A11),DAY(A11)),"MMMM") -> October | C11: 2025 | D11: =SUMIFS('Order Book'!K:K,'Order Book'!E:E,'Resource Performance'!$C$1,'Order Book'!C:C,">="&'Resource Performance'!A11,'Order Book'!C:C,"<="&EOMONTH('Resource Performance'!A11,0)) -> 0 | E11: =SUMIFS(Income!K:K,Income!F:F,'Resource Performance'!$C$1,Income!C:C,">="&'Resource Performance'!A11,Income!C:C,"<="&EOMONTH('Resource Performance'!A11,0)) -> 0 | F11: =D11/$C$4 -> 0 | G11: =IFERROR((D11/D10)-1,0) -> 0 | H11: =IF(D11>=$C$4,$C$6*D11,0) -> 0
A12: =EOMONTH(A11,0)+1 -> 45962 | B12: =TEXT(DATE(C12,MONTH(A12),DAY(A12)),"MMMM") -> November | C12: 2025 | D12: =SUMIFS('Order Book'!K:K,'Order Book'!E:E,'Resource Performance'!$C$1,'Order Book'!C:C,">="&'Resource Performance'!A12,'Order Book'!C:C,"<="&EOMONTH('Resource Performance'!A12,0)) -> 0 | E12: =SUMIFS(Income!K:K,Income!F:F,'Resource Performance'!$C$1,Income!C:C,">="&'Resource Performance'!A12,Income!C:C,"<="&EOMONTH('Resource Performance'!A12,0)) -> 0 | F12: =D12/$C$4 -> 0 | G12: =IFERROR((D12/D11)-1,0) -> 0 | H12: =IF(D12>=$C$4,$C$6*D12,0) -> 0
A13: =EOMONTH(A12,0)+1 -> 45992 | B13: =TEXT(DATE(C13,MONTH(A13),DAY(A13)),"MMMM") -> December | C13: 2025 | D13: =SUMIFS('Order Book'!K:K,'Order Book'!E:E,'Resource Performance'!$C$1,'Order Book'!C:C,">="&'Resource Performance'!A13,'Order Book'!C:C,"<="&EOMONTH('Resource Performance'!A13,0)) -> 0 | E13: =SUMIFS(Income!K:K,Income!F:F,'Resource Performance'!$C$1,Income!C:C,">="&'Resource Performance'!A13,Income!C:C,"<="&EOMONTH('Resource Performance'!A13,0)) -> 0 | F13: =D13/$C$4 -> 0 | G13: =IFERROR((D13/D12)-1,0) -> 0 | H13: =IF(D13>=$C$4,$C$6*D13,0) -> 0
A14: =EOMONTH(A13,0)+1 -> 46023 | B14: =TEXT(DATE(C14,MONTH(A14),DAY(A14)),"MMMM") -> January | C14: 2026 | D14: =SUMIFS('Order Book'!K:K,'Order Book'!E:E,'Resource Performance'!$C$1,'Order Book'!C:C,">="&'Resource Performance'!A14,'Order Book'!C:C,"<="&EOMONTH('Resource Performance'!A14,0)) -> 0 | E14: =SUMIFS(Income!K:K,Income!F:F,'Resource Performance'!$C$1,Income!C:C,">="&'Resource Performance'!A14,Income!C:C,"<="&EOMONTH('Resource Performance'!A14,0)) -> 0 | F14: =D14/$C$4 -> 0 | G14: =IFERROR((D14/D13)-1,0) -> 0 | H14: =IF(D14>=$C$4,$C$6*D14,0) -> 0
A15: =EOMONTH(A14,0)+1 -> 46054 | B15: =TEXT(DATE(C15,MONTH(A15),DAY(A15)),"MMMM") -> February | C15: 2026 | D15: =SUMIFS('Order Book'!K:K,'Order Book'!E:E,'Resource Performance'!$C$1,'Order Book'!C:C,">="&'Resource Performance'!A15,'Order Book'!C:C,"<="&EOMONTH('Resource Performance'!A15,0)) -> 206500 | E15: =SUMIFS(Income!K:K,Income!F:F,'Resource Performance'!$C$1,Income!C:C,">="&'Resource Performance'!A15,Income!C:C,"<="&EOMONTH('Resource Performance'!A15,0)) -> 82600 | F15: =D15/$C$4 -> 0.41717172 | G15: =IFERROR((D15/D14)-1,0) -> 0 | H15: =IF(D15>=$C$4,$C$6*D15,0) -> 0
A16: =EOMONTH(A15,0)+1 -> 46082 | B16: =TEXT(DATE(C16,MONTH(A16),DAY(A16)),"MMMM") -> March | C16: 2026 | D16: =SUMIFS('Order Book'!K:K,'Order Book'!E:E,'Resource Performance'!$C$1,'Order Book'!C:C,">="&'Resource Performance'!A16,'Order Book'!C:C,"<="&EOMONTH('Resource Performance'!A16,0)) -> 0 | E16: =SUMIFS(Income!K:K,Income!F:F,'Resource Performance'!$C$1,Income!C:C,">="&'Resource Performance'!A16,Income!C:C,"<="&EOMONTH('Resource Performance'!A16,0)) -> 0 | F16: =D16/$C$4 -> 0 | G16: =IFERROR((D16/D15)-1,0) -> -1 | H16: =IF(D16>=$C$4,$C$6*D16,0) -> 0
A17: =EOMONTH(A16,0)+1 -> 46113 | B17: =TEXT(DATE(C17,MONTH(A17),DAY(A17)),"MMMM") -> April | C17: 2026 | D17: =SUMIFS('Order Book'!K:K,'Order Book'!E:E,'Resource Performance'!$C$1,'Order Book'!C:C,">="&'Resource Performance'!A17,'Order Book'!C:C,"<="&EOMONTH('Resource Performance'!A17,0)) -> 0 | E17: =SUMIFS(Income!K:K,Income!F:F,'Resource Performance'!$C$1,Income!C:C,">="&'Resource Performance'!A17,Income!C:C,"<="&EOMONTH('Resource Performance'!A17,0)) -> 0 | F17: =D17/$C$4 -> 0 | G17: =IFERROR((D17/D16)-1,0) -> 0 | H17: =IF(D17>=$C$4,$C$6*D17,0) -> 0
A18: =EOMONTH(A17,0)+1 -> 46143 | B18: =TEXT(DATE(C18,MONTH(A18),DAY(A18)),"MMMM") -> May | C18: 2026 | D18: =SUMIFS('Order Book'!K:K,'Order Book'!E:E,'Resource Performance'!$C$1,'Order Book'!C:C,">="&'Resource Performance'!A18,'Order Book'!C:C,"<="&EOMONTH('Resource Performance'!A18,0)) -> 0 | E18: =SUMIFS(Income!K:K,Income!F:F,'Resource Performance'!$C$1,Income!C:C,">="&'Resource Performance'!A18,Income!C:C,"<="&EOMONTH('Resource Performance'!A18,0)) -> 0 | F18: =D18/$C$4 -> 0 | G18: =IFERROR((D18/D17)-1,0) -> 0 | H18: =IF(D18>=$C$4,$C$6*D18,0) -> 0
A19: =EOMONTH(A18,0)+1 -> 46174 | B19: =TEXT(DATE(C19,MONTH(A19),DAY(A19)),"MMMM") -> June | C19: 2026 | D19: =SUMIFS('Order Book'!K:K,'Order Book'!E:E,'Resource Performance'!$C$1,'Order Book'!C:C,">="&'Resource Performance'!A19,'Order Book'!C:C,"<="&EOMONTH('Resource Performance'!A19,0)) -> 0 | E19: =SUMIFS(Income!K:K,Income!F:F,'Resource Performance'!$C$1,Income!C:C,">="&'Resource Performance'!A19,Income!C:C,"<="&EOMONTH('Resource Performance'!A19,0)) -> 0 | F19: =D19/$C$4 -> 0 | G19: =IFERROR((D19/D18)-1,0) -> 0 | H19: =IF(D19>=$C$4,$C$6*D19,0) -> 0
A20: =EOMONTH(A19,0)+1 -> 46204 | B20: =TEXT(DATE(C20,MONTH(A20),DAY(A20)),"MMMM") -> July | C20: 2026 | D20: =SUMIFS('Order Book'!K:K,'Order Book'!E:E,'Resource Performance'!$C$1,'Order Book'!C:C,">="&'Resource Performance'!A20,'Order Book'!C:C,"<="&EOMONTH('Resource Performance'!A20,0)) -> 0 | E20: =SUMIFS(Income!K:K,Income!F:F,'Resource Performance'!$C$1,Income!C:C,">="&'Resource Performance'!A20,Income!C:C,"<="&EOMONTH('Resource Performance'!A20,0)) -> 0 | F20: =D20/$C$4 -> 0 | G20: =IFERROR((D20/D19)-1,0) -> 0 | H20: =IF(D20>=$C$4,$C$6*D20,0) -> 0
A21: =EOMONTH(A20,0)+1 -> 46235 | B21: =TEXT(DATE(C21,MONTH(A21),DAY(A21)),"MMMM") -> August | C21: 2026 | D21: =SUMIFS('Order Book'!K:K,'Order Book'!E:E,'Resource Performance'!$C$1,'Order Book'!C:C,">="&'Resource Performance'!A21,'Order Book'!C:C,"<="&EOMONTH('Resource Performance'!A21,0)) -> 0 | E21: =SUMIFS(Income!K:K,Income!F:F,'Resource Performance'!$C$1,Income!C:C,">="&'Resource Performance'!A21,Income!C:C,"<="&EOMONTH('Resource Performance'!A21,0)) -> 0 | F21: =D21/$C$4 -> 0 | G21: =IFERROR((D21/D20)-1,0) -> 0 | H21: =IF(D21>=$C$4,$C$6*D21,0) -> 0
A22: =EOMONTH(A21,0)+1 -> 46266 | B22: =TEXT(DATE(C22,MONTH(A22),DAY(A22)),"MMMM") -> September | C22: 2026 | D22: =SUMIFS('Order Book'!K:K,'Order Book'!E:E,'Resource Performance'!$C$1,'Order Book'!C:C,">="&'Resource Performance'!A22,'Order Book'!C:C,"<="&EOMONTH('Resource Performance'!A22,0)) -> 0 | E22: =SUMIFS(Income!K:K,Income!F:F,'Resource Performance'!$C$1,Income!C:C,">="&'Resource Performance'!A22,Income!C:C,"<="&EOMONTH('Resource Performance'!A22,0)) -> 0 | F22: =D22/$C$4 -> 0 | G22: =IFERROR((D22/D21)-1,0) -> 0 | H22: =IF(D22>=$C$4,$C$6*D22,0) -> 0
... A25: =EOMONTH(A24,0)+1 -> 46357 | B25: =TEXT(DATE(C25,MONTH(A25),DAY(A25)),"MMMM") -> December | C25: 2026 | D25: =SUMIFS('Order Book'!K:K,'Order Book'!E:E,'Resource Performance'!$C$1,'Order Book'!C:C,">="&'Resource Performance'!A25,'Order Book'!C:C,"<="&EOMONTH('Resource Performance'!A25,0)) -> 0 | E25: =SUMIFS(Income!K:K,Income!F:F,'Resource Performance'!$C$1,Income!C:C,">="&'Resource Performance'!A25,Income!C:C,"<="&EOMONTH('Resource Performance'!A25,0)) -> 0 | F25: =D25/$C$4 -> 0 | G25: =IFERROR((D25/D24)-1,0) -> 0 | H25: =IF(D25>=$C$4,$C$6*D25,0) -> 0
C27: Total - > | D27: =SUM(D10:D26) -> 206500 | E27: =SUM(E10:E26) -> 82600 | H27: =SUM(H10:H26) -> 0

Sheet Balance Amount
A2: Row Labels | B2: Sum of Contract Value(INR) | C2: Sum of Received(INR) | D2: Sum of Balance(INR)
A3: AI LMS Portal | B3: 400000 | C3: 100000 | D3: 300000
A4: Employee India | B4: 250000 | C4: 50000 | D4: 200000
A5: SK Car Finance | B5: 220000 | C5: 50000 | D5: 170000
A6: Farm produce selling app | B6: 190000 | C6: 57000 | D6: 133000
A7: Digital Poster App | B7: 150000 | C7: 35000 | D7: 115000
A8: Taxi App | B8: 104000 | C8: 10000 | D8: 94000
A9: NGK | B9: 225000 | C9: 142111.32 | D9: 82888.68
A10: Indgrocart | B10: 80000 | C10: 0 | D10: 80000
A11: MediConnect | B11: 600000 | C11: 520001 | D11: 79999
A12: Easy Rasta | B12: 150000 | C12: 75000 | D12: 75000
A13: Soya Products-Ecom | B13: 85000 | C13: 11000 | D13: 74000
A14: Local Market Online | B14: 200000 | C14: 140000 | D14: 60000
... A39: Grand Total | B39: 4408000 | C39: 2561612.3 | D39: 1846387.7

Sheet Order Book
A1: Sno | B1: Day | C1: Sale Date | D1: Project Type | E1: Resource | F1: Currency | G1: Project Manager | H1: Project Name | I1: Client Name | J1: Country | K1: Contract Value | L1: Exchange | M1: Contract Value(INR) | N1: Received(INR) | O1: Balance(INR) | P1: Column1 | Q1: Company Financial Snapshot and Next 1-year Projections | T1: Project Manager | U1: Count
A2: 1 | B2: =TEXT(Table1[[#This Row],[Sale Date]], "dddd") -> Monday | C2: 45908 | D2: Android+IOS App | E2: N/A | F2: INR | G2: Chandan+Rishabh | H2: Employee India | I2: Taufeeq | J2: India | K2: 250000 | L2: 1 | M2: =Table1[[#This Row],[Exchange]]*Table1[[#This Row],[Contract Value]] -> 250000 | N2: =SUMIFS(Income!K:K,Income!G:G,Table1[[#This Row],[Project Name]],Income!E:E,Table1[[#This Row],[Project Type]],Income!H:H,Table1[[#This Row],[Client Name]]) -> 50000 | O2: =Table1[[#This Row],[Contract Value(INR)]]-Table1[[#This Row],[Received(INR)]] -> 200000 | Q2: Total Contract | R2: =SUM(M:M) -> 4707510 | T2: Chandan+Rishabh | U2: =COUNTIF(G:G,T2) -> 14
A3: =A2+1 -> 2 | B3: =TEXT(Table1[[#This Row],[Sale Date]], "dddd") -> Tuesday | C3: 45916 | D3: Android App | E3: Prachi Lohani | F3: INR | G3: Vansh+Krishna | H3: Makroo | I3: Umar | J3: India | K3: 60000 | L3: 1 | M3: =Table1[[#This Row],[Exchange]]*Table1[[#This Row],[Contract Value]] -> 60000 | N3: =SUMIFS(Income!K:K,Income!G:G,Table1[[#This Row],[Project Name]],Income!E:E,Table1[[#This Row],[Project Type]],Income!H:H,Table1[[#This Row],[Client Name]]) -> 60000 | O3: =Table1[[#This Row],[Contract Value(INR)]]-Table1[[#This Row],[Received(INR)]] -> 0 | Q3: Total Received | R3: =SUM(N:N) -> 2772222.3 | T3: Vansh+Krishna | U3: =COUNTIF(G:G,T3) -> 23
A4: =A3+1 -> 3 | B4: =TEXT(Table1[[#This Row],[Sale Date]], "dddd") -> Sunday | C4: 45921 | D4: AI | E4: Parul Sandilya | F4: INR | G4: Chandan+Rishabh | H4: AI | I4: Sushil | J4: India | K4: 40000 | L4: 1 | M4: =Table1[[#This Row],[Exchange]]*Table1[[#This Row],[Contract Value]] -> 40000 | N4: =SUMIFS(Income!K:K,Income!G:G,Table1[[#This Row],[Project Name]],Income!E:E,Table1[[#This Row],[Project Type]],Income!H:H,Table1[[#This Row],[Client Name]]) -> 40000 | O4: =Table1[[#This Row],[Contract Value(INR)]]-Table1[[#This Row],[Received(INR)]] -> 0 | Q4: Total Balance | R4: =R2-R3 -> 1935287.7
A5: =A4+1 -> 4 | B5: =TEXT(Table1[[#This Row],[Sale Date]], "dddd") -> Friday | C5: 45926 | D5: Website | E5: N/A | F5: INR | G5: Vansh+Krishna | H5: Brandloomi | I5: Anuj | J5: India | K5: 15000 | L5: 1 | M5: =Table1[[#This Row],[Exchange]]*Table1[[#This Row],[Contract Value]] -> 15000 | N5: =SUMIFS(Income!K:K,Income!G:G,Table1[[#This Row],[Project Name]],Income!E:E,Table1[[#This Row],[Project Type]],Income!H:H,Table1[[#This Row],[Client Name]]) -> 15000 | O5: =Table1[[#This Row],[Contract Value(INR)]]-Table1[[#This Row],[Received(INR)]] -> 0
A6: =A5+1 -> 5 | B6: =TEXT(Table1[[#This Row],[Sale Date]], "dddd") -> Friday | C6: 45926 | D6: Website | E6: N/A | F6: INR | G6: Chandan+Rishabh | H6: Healthy Manushya | I6: Arun Sharma | J6: India | K6: 25000 | L6: 1 | M6: =Table1[[#This Row],[Exchange]]*Table1[[#This Row],[Contract Value]] -> 25000 | N6: =SUMIFS(Income!K:K,Income!G:G,Table1[[#This Row],[Project Name]],Income!E:E,Table1[[#This Row],[Project Type]],Income!H:H,Table1[[#This Row],[Client Name]]) -> 25000 | O6: =Table1[[#This Row],[Contract Value(INR)]]-Table1[[#This Row],[Received(INR)]] -> 0 | T6: Total | U6: =SUM(U2:U4) -> 37
A7: =A6+1 -> 6 | B7: =TEXT(Table1[[#This Row],[Sale Date]], "dddd") -> Friday | C7: 45926 | D7: Android+IOS App | E7: N/A | F7: INR | G7: Vansh+Krishna | H7: Indgrocart | I7: Rajesh | J7: India | K7: 70000 | L7: 1 | M7: =Table1[[#This Row],[Exchange]]*Table1[[#This Row],[Contract Value]] -> 70000 | N7: =SUMIFS(Income!K:K,Income!G:G,Table1[[#This Row],[Project Name]],Income!E:E,Table1[[#This Row],[Project Type]],Income!H:H,Table1[[#This Row],[Client Name]]) -> 0 | O7: =Table1[[#This Row],[Contract Value(INR)]]-Table1[[#This Row],[Received(INR)]] -> 70000 | Q7: Start Date | R7: 45901
A8: =A7+1 -> 7 | B8: =TEXT(Table1[[#This Row],[Sale Date]], "dddd") -> Wednesday | C8: 45931 | D8: Android+IOS App+Website | E8: Prachi Lohani | F8: INR | G8: Vansh+Krishna | H8: MediConnect | I8: Brij | J8: India | K8: 600000 | L8: 1 | M8: =Table1[[#This Row],[Exchange]]*Table1[[#This Row],[Contract Value]] -> 600000 | N8: =SUMIFS(Income!K:K,Income!G:G,Table1[[#This Row],[Project Name]],Income!E:E,Table1[[#This Row],[Project Type]],Income!H:H,Table1[[#This Row],[Client Name]]) -> 520001 | O8: =Table1[[#This Row],[Contract Value(INR)]]-Table1[[#This Row],[Received(INR)]] -> 79999 | Q8: Today | R8: =TODAY() -> 46093
A9: =A8+1 -> 8 | B9: =TEXT(Table1[[#This Row],[Sale Date]], "dddd") -> Friday | C9: 45940 | D9: Android+IOS App | E9: Prachi Lohani | F9: INR | G9: Vansh+Krishna | H9: Fornix | I9: Venket | J9: India | K9: 160000 | L9: 1 | M9: =Table1[[#This Row],[Exchange]]*Table1[[#This Row],[Contract Value]] -> 160000 | N9: =SUMIFS(Income!K:K,Income!G:G,Table1[[#This Row],[Project Name]],Income!E:E,Table1[[#This Row],[Project Type]],Income!H:H,Table1[[#This Row],[Client Name]]) -> 160000 | O9: =Table1[[#This Row],[Contract Value(INR)]]-Table1[[#This Row],[Received(INR)]] -> 0 | Q9: Days Passed Business Operation | R9: =R8-R7 -> 192
A10: =A9+1 -> 9 | B10: =TEXT(Table1[[#This Row],[Sale Date]], "dddd") -> Tuesday | C10: 45944 | D10: AI | E10: N/A | F10: INR | G10: Chandan+Rishabh | H10: Stenna | I10: Madhur Goel | J10: India | K10: 20000 | L10: 1 | M10: =Table1[[#This Row],[Exchange]]*Table1[[#This Row],[Contract Value]] -> 20000 | N10: =SUMIFS(Income!K:K,Income!G:G,Table1[[#This Row],[Project Name]],Income!E:E,Table1[[#This Row],[Project Type]],Income!H:H,Table1[[#This Row],[Client Name]]) -> 20000 | O10: =Table1[[#This Row],[Contract Value(INR)]]-Table1[[#This Row],[Received(INR)]] -> 0 | Q10: Number of Projects | R10: =COUNTA(A:A)-1 -> 39
A11: =A10+1 -> 10 | B11: =TEXT(Table1[[#This Row],[Sale Date]], "dddd") -> Thursday | C11: 45946 | D11: Android+IOS App | E11: Parul Sandilya | F11: INR | G11: Vansh+Krishna | H11: Bla-Bla | I11: Prem Reddy | J11: India | K11: 108000 | L11: 1 | M11: =Table1[[#This Row],[Exchange]]*Table1[[#This Row],[Contract Value]] -> 108000 | N11: =SUMIFS(Income!K:K,Income!G:G,Table1[[#This Row],[Project Name]],Income!E:E,Table1[[#This Row],[Project Type]],Income!H:H,Table1[[#This Row],[Client Name]]) -> 73000 | O11: =Table1[[#This Row],[Contract Value(INR)]]-Table1[[#This Row],[Received(INR)]] -> 35000 | Q11: Days/Project | R11: =R9/R10 -> 4.9230769
A12: =A11+1 -> 11 | B12: =TEXT(Table1[[#This Row],[Sale Date]], "dddd") -> Friday | C12: 45947 | D12: Android+IOS App | E12: Parul Sandilya | F12: INR | G12: Vansh+Krishna | H12: Bhardwaj hospital | I12: Dr Arun | J12: India | K12: 75000 | L12: 1 | M12: =Table1[[#This Row],[Exchange]]*Table1[[#This Row],[Contract Value]] -> 75000 | N12: =SUMIFS(Income!K:K,Income!G:G,Table1[[#This Row],[Project Name]],Income!E:E,Table1[[#This Row],[Project Type]],Income!H:H,Table1[[#This Row],[Client Name]]) -> 52500 | O12: =Table1[[#This Row],[Contract Value(INR)]]-Table1[[#This Row],[Received(INR)]] -> 22500 | Q12: Annual Pojects Projection | R12: =365/R11 -> 74.140625
A13: =A12+1 -> 12 | B13: =TEXT(Table1[[#This Row],[Sale Date]], "dddd") -> Friday | C13: 45947 | D13: Android+IOS App | E13: Parul Sandilya | F13: INR | G13: Vansh+Krishna | H13: Eco Volt Solar | I13: Kuldeep | J13: India | K13: 100000 | L13: 1 | M13: =Table1[[#This Row],[Exchange]]*Table1[[#This Row],[Contract Value]] -> 100000 | N13: =SUMIFS(Income!K:K,Income!G:G,Table1[[#This Row],[Project Name]],Income!E:E,Table1[[#This Row],[Project Type]],Income!H:H,Table1[[#This Row],[Client Name]]) -> 70000 | O13: =Table1[[#This Row],[Contract Value(INR)]]-Table1[[#This Row],[Received(INR)]] -> 30000 | Q13: Average Contact Value | R13: =R2/R10 -> 120705.38
A14: =A13+1 -> 13 | B14: =TEXT(Table1[[#This Row],[Sale Date]], "dddd") -> Wednesday | C14: 45959 | D14: Website | E14: N/A | F14: INR | G14: Vansh+Krishna | H14: Makroo | I14: Umar | J14: India | K14: 12500 | L14: 1 | M14: =Table1[[#This Row],[Exchange]]*Table1[[#This Row],[Contract Value]] -> 12500 | N14: =SUMIFS(Income!K:K,Income!G:G,Table1[[#This Row],[Project Name]],Income!E:E,Table1[[#This Row],[Project Type]],Income!H:H,Table1[[#This Row],[Client Name]]) -> 12500 | O14: =Table1[[#This Row],[Contract Value(INR)]]-Table1[[#This Row],[Received(INR)]] -> 0 | Q14: Next 1 year Contract Value Projection | R14: =R13*R12 -> 8949172.7
A15: =A14+1 -> 14 | B15: =TEXT(Table1[[#This Row],[Sale Date]], "dddd") -> Monday | C15: 45964 | D15: Android+IOS App | E15: Parul Sandilya | F15: INR | G15: Vansh+Krishna | H15: Soya Products-Ecom | I15: M M Mishra | J15: India | K15: 85000 | L15: 1 | M15: =Table1[[#This Row],[Exchange]]*Table1[[#This Row],[Contract Value]] -> 85000 | N15: =SUMIFS(Income!K:K,Income!G:G,Table1[[#This Row],[Project Name]],Income!E:E,Table1[[#This Row],[Project Type]],Income!H:H,Table1[[#This Row],[Client Name]]) -> 11000 | O15: =Table1[[#This Row],[Contract Value(INR)]]-Table1[[#This Row],[Received(INR)]] -> 74000
A16: =A15+1 -> 15 | B16: =TEXT(Table1[[#This Row],[Sale Date]], "dddd") -> Wednesday | C16: 45973 | D16: Android+IOS App | E16: N/A | F16: INR | G16: Chandan+Rishabh | H16: Degree India | I16: Taufeeq | J16: India | K16: 30000 | L16: 1 | M16: =Table1[[#This Row],[Exchange]]*Table1[[#This Row],[Contract Value]] -> 30000 | N16: =SUMIFS(Income!K:K,Income!G:G,Table1[[#This Row],[Project Name]],Income!E:E,Table1[[#This Row],[Project Type]],Income!H:H,Table1[[#This Row],[Client Name]]) -> 30000 | O16: =Table1[[#This Row],[Contract Value(INR)]]-Table1[[#This Row],[Received(INR)]] -> 0 | Q16: Start Date | R16: 45901
A17: =A16+1 -> 16 | B17: =TEXT(Table1[[#This Row],[Sale Date]], "dddd") -> Friday | C17: 45975 | D17: Website | E17: N/A | F17: INR | G17: Chandan+Rishabh | H17: Enlightify | I17: Apoorv | J17: India | K17: 25000 | L17: 1 | M17: =Table1[[#This Row],[Exchange]]*Table1[[#This Row],[Contract Value]] -> 25000 | N17: =SUMIFS(Income!K:K,Income!G:G,Table1[[#This Row],[Project Name]],Income!E:E,Table1[[#This Row],[Project Type]],Income!H:H,Table1[[#This Row],[Client Name]]) -> 7000 | O17: =Table1[[#This Row],[Contract Value(INR)]]-Table1[[#This Row],[Received(INR)]] -> 18000 | Q17: Calculation Date | R17: 46087
A18: =A17+1 -> 17 | B18: =TEXT(Table1[[#This Row],[Sale Date]], "dddd") -> Saturday | C18: 45976 | D18: Android+IOS App | E18: Haider | F18: INR | G18: Chandan+Rishabh | H18: Easy Rasta | I18: Dennis Anthony | J18: India | K18: 150000 | L18: 1 | M18: =Table1[[#This Row],[Exchange]]*Table1[[#This Row],[Contract Value]] -> 150000 | N18: =SUMIFS(Income!K:K,Income!G:G,Table1[[#This Row],[Project Name]],Income!E:E,Table1[[#This Row],[Project Type]],Income!H:H,Table1[[#This Row],[Client Name]]) -> 75000 | O18: =Table1[[#This Row],[Contract Value(INR)]]-Table1[[#This Row],[Received(INR)]] -> 75000 | Q18: Marketing Project Aquired | R18: =COUNTIF(E:E,"Prachi Lohani")+COUNTIF(E:E,"Parul Sandilya")++COUNTIF(E:E,"Haider") -> 21
A19: =A18+1 -> 18 | B19: =TEXT(Table1[[#This Row],[Sale Date]], "dddd") -> Thursday | C19: 45981 | D19: Android+IOS App | E19: Parul Sandilya | F19: INR | G19: Vansh+Krishna | H19: FitLeap | I19: Babu Raj | J19: India | K19: 160000 | L19: 1 | M19: =Table1[[#This Row],[Exchange]]*Table1[[#This Row],[Contract Value]] -> 160000 | N19: =SUMIFS(Income!K:K,Income!G:G,Table1[[#This Row],[Project Name]],Income!E:E,Table1[[#This Row],[Project Type]],Income!H:H,Table1[[#This Row],[Client Name]]) -> 120000 | O19: =Table1[[#This Row],[Contract Value(INR)]]-Table1[[#This Row],[Received(INR)]] -> 40000 | Q19: Total FB Budget till 02-02-2026 | R19: 276016.16
A20: =A19+1 -> 19 | B20: =TEXT(Table1[[#This Row],[Sale Date]], "dddd") -> Friday | C20: 45982 | D20: Android+IOS App | E20: Haider | F20: INR | G20: Vansh+Krishna | H20: SK Car Finance | I20: Prateek Srivastava | J20: India | K20: 220000 | L20: 1 | M20: =Table1[[#This Row],[Exchange]]*Table1[[#This Row],[Contract Value]] -> 220000 | N20: =SUMIFS(Income!K:K,Income!G:G,Table1[[#This Row],[Project Name]],Income!E:E,Table1[[#This Row],[Project Type]],Income!H:H,Table1[[#This Row],[Client Name]]) -> 50000 | O20: =Table1[[#This Row],[Contract Value(INR)]]-Table1[[#This Row],[Received(INR)]] -> 170000 | Q20: Office Fixed Cost | R20: =50000*_xlfn.DAYS(R17,R16)/30 -> 310000 | S20: Taken 50k fixed cost for office
A21: =A20+1 -> 20 | B21: =TEXT(Table1[[#This Row],[Sale Date]], "dddd") -> Tuesday | C21: 45986 | D21: Android+IOS App | E21: N/A | F21: INR | G21: Chandan+Rishabh | H21: NGK | I21: Strini Naidu | J21: South Africa | K21: 2500 | L21: 90 | M21: =Table1[[#This Row],[Exchange]]*Table1[[#This Row],[Contract Value]] -> 225000 | N21: =SUMIFS(Income!K:K,Income!G:G,Table1[[#This Row],[Project Name]],Income!E:E,Table1[[#This Row],[Project Type]],Income!H:H,Table1[[#This Row],[Client Name]]) -> 142111.32 | O21: =Table1[[#This Row],[Contract Value(INR)]]-Table1[[#This Row],[Received(INR)]] -> 82888.68 | Q21: Marketing Salaries
A22: =A21+1 -> 21 | B22: =TEXT(Table1[[#This Row],[Sale Date]], "dddd") -> Thursday | C22: 45988 | D22: Android+IOS App+Website | E22: Parul Sandilya | F22: INR | G22: Chandan+Rishabh | H22: Local Market Online | I22: Vinod Khosla | J22: India | K22: 200000 | L22: 1 | M22: =Table1[[#This Row],[Exchange]]*Table1[[#This Row],[Contract Value]] -> 200000 | N22: =SUMIFS(Income!K:K,Income!G:G,Table1[[#This Row],[Project Name]],Income!E:E,Table1[[#This Row],[Project Type]],Income!H:H,Table1[[#This Row],[Client Name]]) -> 140000 | O22: =Table1[[#This Row],[Contract Value(INR)]]-Table1[[#This Row],[Received(INR)]] -> 60000 | Q22: Parul
A23: =A22+1 -> 22 | B23: =TEXT(Table1[[#This Row],[Sale Date]], "dddd") -> Saturday | C23: 45990 | D23: Android+IOS App | E23: Haider | F23: INR | G23: Chandan+Rishabh | H23: School Management App | I23: Amitosh Chaudhary | J23: India | K23: 212500 | L23: 1 | M23: =Table1[[#This Row],[Exchange]]*Table1[[#This Row],[Contract Value]] -> 212500 | N23: =SUMIFS(Income!K:K,Income!G:G,Table1[[#This Row],[Project Name]],Income!E:E,Table1[[#This Row],[Project Type]],Income!H:H,Table1[[#This Row],[Client Name]]) -> 205000 | O23: =Table1[[#This Row],[Contract Value(INR)]]-Table1[[#This Row],[Received(INR)]] -> 7500 | Q23: Prachi
A24: =A23+1 -> 23 | B24: =TEXT(Table1[[#This Row],[Sale Date]], "dddd") -> Monday | C24: 45992 | D24: Android App | E24: Parul Sandilya | F24: INR | G24: Vansh+Krishna | H24: Real estate Data Management | I24: Akash Tripathi | J24: India | K24: 80000 | L24: 1 | M24: =Table1[[#This Row],[Exchange]]*Table1[[#This Row],[Contract Value]] -> 80000 | N24: =SUMIFS(Income!K:K,Income!G:G,Table1[[#This Row],[Project Name]],Income!E:E,Table1[[#This Row],[Project Type]],Income!H:H,Table1[[#This Row],[Client Name]]) -> 56000 | O24: =Table1[[#This Row],[Contract Value(INR)]]-Table1[[#This Row],[Received(INR)]] -> 24000 | Q24: Haider
A25: =A24+1 -> 24 | B25: =TEXT(Table1[[#This Row],[Sale Date]], "dddd") -> Tuesday | C25: 45993 | D25: Android+IOS App+Website | E25: Parul Sandilya | F25: INR | G25: Vansh+Krishna | H25: Agriebookhub | I25: Sanjay Kumar | J25: India | K25: 100000 | L25: 1 | M25: =Table1[[#This Row],[Exchange]]*Table1[[#This Row],[Contract Value]] -> 100000 | N25: =SUMIFS(Income!K:K,Income!G:G,Table1[[#This Row],[Project Name]],Income!E:E,Table1[[#This Row],[Project Type]],Income!H:H,Table1[[#This Row],[Client Name]]) -> 100000 | O25: =Table1[[#This Row],[Contract Value(INR)]]-Table1[[#This Row],[Received(INR)]] -> 0 | Q25: Total Marketing Salaries | R25: =SUM(R22:R24) -> 0
A26: =A25+1 -> 25 | B26: =TEXT(Table1[[#This Row],[Sale Date]], "dddd") -> Friday | C26: 45996 | D26: Android+IOS App | E26: Haider | F26: INR | G26: Vansh+Krishna | H26: Digital Poster App | I26: Gaurav Shashti | J26: India | K26: 150000 | L26: 1 | M26: =Table1[[#This Row],[Exchange]]*Table1[[#This Row],[Contract Value]] -> 150000 | N26: =SUMIFS(Income!K:K,Income!G:G,Table1[[#This Row],[Project Name]],Income!E:E,Table1[[#This Row],[Project Type]],Income!H:H,Table1[[#This Row],[Client Name]]) -> 35000 | O26: =Table1[[#This Row],[Contract Value(INR)]]-Table1[[#This Row],[Received(INR)]] -> 115000 | Q26: Marketing Commisions | R26: 21250
A27: =A26+1 -> 26 | B27: =TEXT(Table1[[#This Row],[Sale Date]], "dddd") -> Thursday | C27: 46002 | D27: Android+IOS App | E27: Haider | F27: INR | G27: Vansh+Krishna | H27: Engineered Hybrid Ride-Sharing Platform | I27: Srishylam Jadi | J27: India | K27: 165000 | L27: 1 | M27: =Table1[[#This Row],[Exchange]]*Table1[[#This Row],[Contract Value]] -> 165000 | N27: =SUMIFS(Income!K:K,Income!G:G,Table1[[#This Row],[Project Name]],Income!E:E,Table1[[#This Row],[Project Type]],Income!H:H,Table1[[#This Row],[Client Name]]) -> 115500 | O27: =Table1[[#This Row],[Contract Value(INR)]]-Table1[[#This Row],[Received(INR)]] -> 49500
A28: =A27+1 -> 27 | B28: =TEXT(Table1[[#This Row],[Sale Date]], "dddd") -> Monday | C28: 46006 | D28: Android+IOS App | E28: Parul Sandilya | F28: INR | G28: Vansh+Krishna | H28: OTT App | I28: VanLal | J28: India | K28: 100000 | L28: 1 | M28: =Table1[[#This Row],[Exchange]]*Table1[[#This Row],[Contract Value]] -> 100000 | N28: =SUMIFS(Income!K:K,Income!G:G,Table1[[#This Row],[Project Name]],Income!E:E,Table1[[#This Row],[Project Type]],Income!H:H,Table1[[#This Row],[Client Name]]) -> 50000 | O28: =Table1[[#This Row],[Contract Value(INR)]]-Table1[[#This Row],[Received(INR)]] -> 50000
A29: =A28+1 -> 28 | B29: =TEXT(Table1[[#This Row],[Sale Date]], "dddd") -> Friday | C29: 46017 | D29: Website | E29: N/A | F29: INR | G29: Chandan+Rishabh | H29: GamifyIAS | I29: Amogh | J29: India | K29: 31000 | L29: 1 | M29: =Table1[[#This Row],[Exchange]]*Table1[[#This Row],[Contract Value]] -> 31000 | N29: =SUMIFS(Income!K:K,Income!G:G,Table1[[#This Row],[Project Name]],Income!E:E,Table1[[#This Row],[Project Type]],Income!H:H,Table1[[#This Row],[Client Name]]) -> 0 | O29: =Table1[[#This Row],[Contract Value(INR)]]-Table1[[#This Row],[Received(INR)]] -> 31000
A30: =A29+1 -> 29 | B30: =TEXT(Table1[[#This Row],[Sale Date]], "dddd") -> Monday | C30: 46020 | D30: Android+IOS App | E30: Parul Sandilya | F30: INR | G30: Vansh+Krishna | H30: Taxi App | I30: Md Aslam | J30: India | K30: 104000 | L30: 1 | M30: =Table1[[#This Row],[Exchange]]*Table1[[#This Row],[Contract Value]] -> 104000 | N30: =SUMIFS(Income!K:K,Income!G:G,Table1[[#This Row],[Project Name]],Income!E:E,Table1[[#This Row],[Project Type]],Income!H:H,Table1[[#This Row],[Client Name]]) -> 10000 | O30: =Table1[[#This Row],[Contract Value(INR)]]-Table1[[#This Row],[Received(INR)]] -> 94000
A31: =A30+1 -> 30 | B31: =TEXT(Table1[[#This Row],[Sale Date]], "dddd") -> Monday | C31: 46034 | D31: Android+IOS App | E31: Haider | F31: INR | G31: Vansh+Krishna | H31: Urban Elite | I31: Mahendra | J31: India | K31: 85000 | L31: 1 | M31: =Table1[[#This Row],[Exchange]]*Table1[[#This Row],[Contract Value]] -> 85000 | N31: =SUMIFS(Income!K:K,Income!G:G,Table1[[#This Row],[Project Name]],Income!E:E,Table1[[#This Row],[Project Type]],Income!H:H,Table1[[#This Row],[Client Name]]) -> 50000 | O31: =Table1[[#This Row],[Contract Value(INR)]]-Table1[[#This Row],[Received(INR)]] -> 35000
A32: =A31+1 -> 31 | B32: =TEXT(Table1[[#This Row],[Sale Date]], "dddd") -> Thursday | C32: 46037 | D32: Website | E32: N/A | F32: INR | G32: Vansh+Krishna | H32: Fornix-website | I32: Venket | J32: India | K32: 60000 | L32: 1 | M32: =Table1[[#This Row],[Exchange]]*Table1[[#This Row],[Contract Value]] -> 60000 | N32: =SUMIFS(Income!K:K,Income!G:G,Table1[[#This Row],[Project Name]],Income!E:E,Table1[[#This Row],[Project Type]],Income!H:H,Table1[[#This Row],[Client Name]]) -> 60000 | O32: =Table1[[#This Row],[Contract Value(INR)]]-Table1[[#This Row],[Received(INR)]] -> 0 | Q32: Total Marketing Expenses | R32: =R25+R19+R20+R26 -> 607266.16
A33: =A32+1 -> 32 | B33: =TEXT(Table1[[#This Row],[Sale Date]], "dddd") -> Monday | C33: 46055 | D33: Android+IOS App+Website | E33: N/A | F33: INR | G33: Chandan+Rishabh | H33: AI LMS Portal | I33: Arun Swamy | J33: India | K33: 400000 | L33: 1 | M33: =Table1[[#This Row],[Exchange]]*Table1[[#This Row],[Contract Value]] -> 400000 | N33: =SUMIFS(Income!K:K,Income!G:G,Table1[[#This Row],[Project Name]],Income!E:E,Table1[[#This Row],[Project Type]],Income!H:H,Table1[[#This Row],[Client Name]]) -> 150000 | O33: =Table1[[#This Row],[Contract Value(INR)]]-Table1[[#This Row],[Received(INR)]] -> 250000 | Q33: Total Contract wins | R33: =SUMIFS(M:M,E:E,"Prachi Lohani")+SUMIFS(M:M,E:E,"Parul Sandilya")++SUMIFS(M:M,E:E,"Haider") -> 3144500
A34: =A33+1 -> 33 | B34: =TEXT(Table1[[#This Row],[Sale Date]], "dddd") -> Wednesday | C34: 46057 | D34: Android+IOS App+Website | E34: N/A | F34: INR | G34: Vansh+Krishna | H34: Local Market Online-AI work | I34: Vinod Khosla | J34: India | K34: 25000 | L34: 1 | M34: =Table1[[#This Row],[Exchange]]*Table1[[#This Row],[Contract Value]] -> 25000 | N34: =SUMIFS(Income!K:K,Income!G:G,Table1[[#This Row],[Project Name]],Income!E:E,Table1[[#This Row],[Project Type]],Income!H:H,Table1[[#This Row],[Client Name]]) -> 25000 | O34: =Table1[[#This Row],[Contract Value(INR)]]-Table1[[#This Row],[Received(INR)]] -> 0 | Q34: ROAS | R34: =R33/R19 -> 11.392449
A35: =A34+1 -> 34 | B35: =TEXT(Table1[[#This Row],[Sale Date]], "dddd") -> Thursday | C35: 46058 | D35: Website | E35: N/A | F35: INR | G35: Chandan+Rishabh | H35: Stenna-website | I35: Madhur Goel | J35: India | K35: 50000 | L35: 1 | M35: =Table1[[#This Row],[Exchange]]*Table1[[#This Row],[Contract Value]] -> 50000 | N35: =SUMIFS(Income!K:K,Income!G:G,Table1[[#This Row],[Project Name]],Income!E:E,Table1[[#This Row],[Project Type]],Income!H:H,Table1[[#This Row],[Client Name]]) -> 50000 | O35: =Table1[[#This Row],[Contract Value(INR)]]-Table1[[#This Row],[Received(INR)]] -> 0
A36: =A35+1 -> 35 | B36: =TEXT(Table1[[#This Row],[Sale Date]], "dddd") -> Monday | C36: 46076 | D36: Android+IOS App+Website | E36: Haider | F36: INR | H36: Farm produce selling app | I36: Sadiq | J36: India | K36: 190000 | L36: 1 | M36: =Table1[[#This Row],[Exchange]]*Table1[[#This Row],[Contract Value]] -> 190000 | N36: =SUMIFS(Income!K:K,Income!G:G,Table1[[#This Row],[Project Name]],Income!E:E,Table1[[#This Row],[Project Type]],Income!H:H,Table1[[#This Row],[Client Name]]) -> 57000 | O36: =Table1[[#This Row],[Contract Value(INR)]]-Table1[[#This Row],[Received(INR)]] -> 133000 | Q36: Customer Acquisition cost(CAC) | R36: =R32/R18 -> 28917.436
A37: =A36+1 -> 36 | B37: =TEXT(Table1[[#This Row],[Sale Date]], "dddd") -> Wednesday | C37: 46078 | D37: Android+IOS App+Website | E37: N/A | F37: INR | G37: Vansh+Krishna | H37: Beingpetz | I37: Mahesh | J37: India | K37: 15010 | L37: 1 | M37: =Table1[[#This Row],[Exchange]]*Table1[[#This Row],[Contract Value]] -> 15010 | N37: =SUMIFS(Income!K:K,Income!G:G,Table1[[#This Row],[Project Name]],Income!E:E,Table1[[#This Row],[Project Type]],Income!H:H,Table1[[#This Row],[Client Name]]) -> 15010 | O37: =Table1[[#This Row],[Contract Value(INR)]]-Table1[[#This Row],[Received(INR)]] -> 0
A38: =A37+1 -> 37 | B38: =TEXT(Table1[[#This Row],[Sale Date]], "dddd") -> Wednesday | C38: 46078 | D38: AI | E38: N/A | F38: INR | G38: Chandan+Rishabh | H38: AI-maintenance | I38: Sushil | J38: India | K38: 8000 | L38: 1 | M38: =Table1[[#This Row],[Exchange]]*Table1[[#This Row],[Contract Value]] -> 8000 | N38: =SUMIFS(Income!K:K,Income!G:G,Table1[[#This Row],[Project Name]],Income!E:E,Table1[[#This Row],[Project Type]],Income!H:H,Table1[[#This Row],[Client Name]]) -> 8000 | O38: =Table1[[#This Row],[Contract Value(INR)]]-Table1[[#This Row],[Received(INR)]] -> 0 | Q38: Total Fixed Cost | R38: =Staff!D33*12 -> 6936000
A39: =A38+1 -> 38 | B39: =TEXT(Table1[[#This Row],[Sale Date]], "dddd") -> Saturday | C39: 46081 | D39: Android+IOS App | E39: Akansha | F39: INR | H39: Zippy Equestrian Center | I39: Dilip | J39: India | K39: 206500 | L39: 1 | M39: =Table1[[#This Row],[Exchange]]*Table1[[#This Row],[Contract Value]] -> 206500 | N39: =SUMIFS(Income!K:K,Income!G:G,Table1[[#This Row],[Project Name]],Income!E:E,Table1[[#This Row],[Project Type]],Income!H:H,Table1[[#This Row],[Client Name]]) -> 82600 | O39: =Table1[[#This Row],[Contract Value(INR)]]-Table1[[#This Row],[Received(INR)]] -> 123900 | Q39: Net Profit Before TAX(EBIDA) | R39: =R14-R38 -> 2013172.7
A40: =A39+1 -> 39 | B40: =TEXT(Table1[[#This Row],[Sale Date]], "dddd") -> Thursday | C40: 46086 | D40: Android+IOS App | E40: N/A | F40: INR | G40: Vansh+Krishna | H40: Beingpetz - Phase 2 | I40: Mahesh | J40: India | K40: 95000 | L40: 1 | M40: =Table1[[#This Row],[Exchange]]*Table1[[#This Row],[Contract Value]] -> 95000 | N40: =SUMIFS(Income!K:K,Income!G:G,Table1[[#This Row],[Project Name]],Income!E:E,Table1[[#This Row],[Project Type]],Income!H:H,Table1[[#This Row],[Client Name]]) -> 30000 | O40: =Table1[[#This Row],[Contract Value(INR)]]-Table1[[#This Row],[Received(INR)]] -> 65000 | Q40: Tax(25% for Pvt Ltd) | R40: =R39*25% -> 503293.16
M41: =Table1[[#This Row],[Exchange]]*Table1[[#This Row],[Contract Value]] -> 0 | N41: =SUMIFS(Income!K:K,Income!G:G,Table1[[#This Row],[Project Name]],Income!E:E,Table1[[#This Row],[Project Type]],Income!H:H,Table1[[#This Row],[Client Name]]) -> 0 | O41: =Table1[[#This Row],[Contract Value(INR)]]-Table1[[#This Row],[Received(INR)]] -> 0 | Q41: PAT | R41: =R39-R40 -> 1509879.5
M42: =Table1[[#This Row],[Exchange]]*Table1[[#This Row],[Contract Value]] -> 0 | N42: =SUMIFS(Income!K:K,Income!G:G,Table1[[#This Row],[Project Name]],Income!E:E,Table1[[#This Row],[Project Type]],Income!H:H,Table1[[#This Row],[Client Name]]) -> 0 | O42: =Table1[[#This Row],[Contract Value(INR)]]-Table1[[#This Row],[Received(INR)]] -> 0 | Q42: Per partner/month | R42: =R41/5/12 -> 25164.658
M43: =Table1[[#This Row],[Exchange]]*Table1[[#This Row],[Contract Value]] -> 0 | N43: =SUMIFS(Income!K:K,Income!G:G,Table1[[#This Row],[Project Name]],Income!E:E,Table1[[#This Row],[Project Type]],Income!H:H,Table1[[#This Row],[Client Name]]) -> 0 | O43: =Table1[[#This Row],[Contract Value(INR)]]-Table1[[#This Row],[Received(INR)]] -> 0

Sheet Pending Payment
A1: Project Name | B1: Contact value | C1: part 1 | D1: Amount | E1: Receieved | F1: Pending | G1: part 2 | H1: Amount | I1: Receieved | J1: Pending | K1: part 3 | L1: Amount | M1: Receieved | N1: Pending | O1: Current Pending | P1: Total Pending
A2: Bhardwaj hospital | B2: 75000 | C2: 0.4 | D2: =C2*B2 -> 30000 | E2: 22500 | F2: =D2-E2 -> 7500 | G2: 0.3 | H2: =G2*$B$2 -> 22500 | I2: 0 | J2: =H2-I2 -> 22500 | K2: 0.3 | L2: =K2*$B$2 -> 22500 | M2: 0 | N2: =L2-M2 -> 22500 | O2: =F2+J2 -> 30000 | P2: =N2+J2+F2 -> 52500
A5: Project Name | B5: Contact value | C5: part 1 | D5: Amount | E5: Receieved | F5: Pending | G5: part 2 | H5: Amount | I5: Receieved | J5: Pending | K5: part 3 | L5: Amount | M5: Receieved | N5: Pending | O5: Current Pending | P5: Total Pending
A6: Bhardwaj hospital | B6: 108000 | C6: 0.4 | D6: =C6*B6 -> 43200 | E6: 39000 | F6: =D6-E6 -> 4200 | G6: 0.3 | H6: =G6*$B$2 -> 22500 | I6: 0 | J6: =H6-I6 -> 22500 | K6: 0.3 | L6: =K6*$B$2 -> 22500 | M6: 0 | N6: =L6-M6 -> 22500 | O6: =F6+J6 -> 26700 | P6: =N6+J6+F6 -> 49200
A8: Total | B8: =B6 -> 108000
A9: Received | B9: =E6 -> 39000
A10: Total Pending | B10: =B8-B9 -> 69000
A11: Part 2 | B11: 34000
A12: On Deployment | B12: =B8-B9-B11 -> 35000
A18: Project Name | B18: Contact value | C18: part 1 | D18: Amount | E18: Receieved | F18: Pending | G18: part 2 | H18: Amount | I18: Receieved | J18: Pending | K18: part 3 | L18: Amount | M18: Receieved | N18: Pending | O18: Current Pending | P18: Total Pending
A19: Eco Volt | B19: 100000 | C19: 0.4 | D19: =C19*B19 -> 40000 | E19: 40000 | F19: =D19-E19 -> 0 | G19: 0.3 | H19: 30000 | I19: 0 | J19: =H19-I19 -> 30000 | K19: 0.3 | L19: 30000 | M19: 0 | N19: =L19-M19 -> 30000 | O19: =F19+J19 -> 30000 | P19: =N19+J19+F19 -> 60000
A21: Total | B21: =B19 -> 100000
A22: Received | B22: =E19 -> 40000
A23: Total Pending | B23: =B21-B22 -> 60000
A24: Part 2 | B24: =H19 -> 30000
A25: On Deployment | B25: =B21-B22-B24 -> 30000

Sheet Validations
A1: Deliverables | B1: Resource | C1: Category | D1: Type of sale | E1: Mode of Payment | F1: Project Manager | G1: Project Status | I1: Name | J1: Joining | K1: Last working | M1: Fund raising | N1: 46050 | P1: Argosmob Tech and AI Pvt Ltd
A2: Android App | B2: Parul Sandilya | C2: Marketing | D2: New Acquisition | E2: Axis Bank UPI | F2: Chandan | G2: Prototype | I2: Parul | K2: 46022 | P2: Sno | Q2: Particulars | R2: Details
A3: IOS App | B3: Prachi Lohani | C3: Office expense | D3: Old Acquisition | E3: PhonePe | F3: Krishna | G3: Front end | I3: Prachi | K3: 46022 | P3: 1 | Q3: Total Equity Investment | R3: 2000000
A4: Android+IOS App | B4: Haider | C4: Ac repair | D4: N/A | E4: Net Banking | F4: Vansh | G4: Back end | P4: 2 | Q4: Loan Amount | R4: 1000000
A5: Android App+Website | B5: N/A | C5: Food | E5: UPI | G5: API creation | P5: 3 | Q5: Loan Tenure | R5: 2 Years
A6: Android+IOS App+Website | B6: Avani Shee | C6: Electricity Recharge | E6: Cash | G6: API Integration | P6: 4 | Q6: Loan Interest Rate | R6: 0% (Interest Free)
A7: Website | B7: Akansha | C7: Dialer recharge | E7: Gateway | G7: Testing | P7: 5 | Q7: Total Number of Partners | R7: 5
A8: AI | C8: Fixed Expense | G8: Delivered | P8: 6 | Q8: Director Salary | R8: ₹25,000 per Director per month
A9: Digital Marketing | C9: Self Funding | G9: Not Started | P9: 7 | Q9: Non-Compete Clause | R9: Applicable to all partners
A10: Video Editing | C10: Fixed
A11: Graphic Designing | C11: Fun
C12: Self Withdrawl | P12: Argosmob Tech and AI Pvt Ltd(Equity Distribution)
C13: Cross Funding | P13: Sno | Q13: Partner Name | R13: Equity Share (%)
C14: Salary | P14: 1 | Q14: Chandan | R14: 0.2
C15: Commisions | P15: 3 | Q15: Krishna | R15: 0.2
C16: Bank Expenses | P16: 4 | Q16: Rishabh | R16: 0.2
C17: Client Expenses | P17: 2 | Q17: Vansh | R17: 0.2
C18: Tax | P18: 5 | Q18: Vineet Chaddha Sir & Jitendra Sir (Combined) | R18: 0.2
C19: Misc
C20: Equity | Q20: Total | R20: 1
C21: Loan

Sheet Project Deadlines
A1: Sno | B1: Sale Date | C1: Project Manager | D1: Maintenance | E1: Maintenance-Amount | F1: Project Name | G1: Client Name | H1: Status | I1: City | J1: Days Passed | K1: Duration(Days) | L1: Deadline | M1: Time left | N1: Pending Amount | O1: Next Payment Amount | P1: Next Payment Date | Q1: Column1 | R1: Project Manager | S1: Pending Amount | T1: Person
A2: 1 | B2: 45916 | C2: Krishna | D2: Client server | E2: 5000 | F2: Makroo | G2: Umar | H2: Delivered | J2: =_xlfn.DAYS(TODAY(),B2) -> 177 | K2: 60 | L2: =K2+B2 -> 45976 | M2: =IF(H2<>"Delivered",_xlfn.DAYS(L2,TODAY()),"Delivered") -> Delivered | N2: =VLOOKUP(F2,Table1[[#All],[Project Name]:[Balance(INR)]],8,0) -> 0 | R2: Chandan | S2: =SUMIF(C:C,R2,N:N) -> 474388.68
A3: =A2+1 -> 2 | B3: 45921 | C3: Chandan | D3: Self hosted n8n | E3: 5000 | F3: AI | G3: Sushil | H3: Delivered | J3: =_xlfn.DAYS(TODAY(),B3) -> 172 | L3: =K3+B3 -> 45921 | M3: =IF(H3<>"Delivered",_xlfn.DAYS(L3,TODAY()),"Delivered") -> Delivered | N3: =VLOOKUP(F3,Table1[[#All],[Project Name]:[Balance(INR)]],8,0) -> 0 | R3: Vansh | S3: =SUMIF(C:C,R3,N:N) -> 751999
A4: =A3+1 -> 3 | B4: 45926 | C4: Vansh | D4: Client server | E4: 0 | F4: Brandloomi | G4: Anuj | H4: Delivered | J4: =_xlfn.DAYS(TODAY(),B4) -> 167 | L4: =K4+B4 -> 45926 | M4: =IF(H4<>"Delivered",_xlfn.DAYS(L4,TODAY()),"Delivered") -> Delivered | N4: =VLOOKUP(F4,Table1[[#All],[Project Name]:[Balance(INR)]],8,0) -> 0 | R4: Krishna | S4: =SUMIF(C:C,R4,N:N) -> 137000
A5: =A4+1 -> 4 | B5: 45926 | C5: Chandan | D5: Client server-shopify | E5: 0 | F5: Healthy Manushya | G5: Arun Sharma | H5: Delivered | J5: =_xlfn.DAYS(TODAY(),B5) -> 167 | L5: =K5+B5 -> 45926 | M5: =IF(H5<>"Delivered",_xlfn.DAYS(L5,TODAY()),"Delivered") -> Delivered | N5: =VLOOKUP(F5,Table1[[#All],[Project Name]:[Balance(INR)]],8,0) -> 0
A6: =A5+1 -> 5 | B6: 45944 | C6: Chandan | D6: Self hosted n8n | E6: 15000 | F6: Stenna | G6: Madhur Goel | H6: Delivered | J6: =_xlfn.DAYS(TODAY(),B6) -> 149 | L6: =K6+B6 -> 45944 | M6: =IF(H6<>"Delivered",_xlfn.DAYS(L6,TODAY()),"Delivered") -> Delivered | N6: =VLOOKUP(F6,Table1[[#All],[Project Name]:[Balance(INR)]],8,0) -> 0 | R6: Total | S6: =SUM(S2:S5) -> 1363387.7
A7: =A6+1 -> 6 | B7: 45959 | C7: Krishna | D7: Client server | E7: 0 | F7: Makroo | G7: Umar | H7: Delivered | J7: =_xlfn.DAYS(TODAY(),B7) -> 134 | L7: =K7+B7 -> 45959 | M7: =IF(H7<>"Delivered",_xlfn.DAYS(L7,TODAY()),"Delivered") -> Delivered | N7: =VLOOKUP(F7,Table1[[#All],[Project Name]:[Balance(INR)]],8,0) -> 0
A8: =A7+1 -> 7 | B8: 45993 | C8: Vansh | D8: Testing-self | E8: 0 | F8: Agriebookhub | G8: Sanjay Kumar | H8: Delivered | J8: =_xlfn.DAYS(TODAY(),B8) -> 100 | K8: 50 | L8: =K8+B8 -> 46043 | M8: =IF(H8<>"Delivered",_xlfn.DAYS(L8,TODAY()),"Delivered") -> Delivered | N8: =VLOOKUP(F8,Table1[[#All],[Project Name]:[Balance(INR)]],8,0) -> 0
A9: =A8+1 -> 8 | B9: 46037 | C9: Vansh | D9: Testing-self | E9: 0 | F9: Fornix-website | G9: Venket | H9: Delivered | J9: =_xlfn.DAYS(TODAY(),B9) -> 56 | K9: 25 | L9: =K9+B9 -> 46062 | M9: =IF(H9<>"Delivered",_xlfn.DAYS(L9,TODAY()),"Delivered") -> Delivered | N9: =VLOOKUP(F9,Table1[[#All],[Project Name]:[Balance(INR)]],8,0) -> 0
A10: =A9+1 -> 9 | B10: 45981 | C10: Vansh | D10: Testing-self | E10: 5000 | F10: FitLeap | G10: Babu Raj | H10: API Integration | J10: =_xlfn.DAYS(TODAY(),B10) -> 112 | K10: 110 | L10: =K10+B10 -> 46091 | M10: =IF(H10<>"Delivered",_xlfn.DAYS(L10,TODAY()),"Delivered") -> -2 | N10: =VLOOKUP(F10,Table1[[#All],[Project Name]:[Balance(INR)]],8,0) -> 40000 | O10: 40000 | T10: Dubey
A11: =A10+1 -> 10 | B11: 45990 | C11: Chandan | D11: Testing-self | E11: 15000 | F11: School Management App | G11: Amitosh Chaudhary | H11: Testing | J11: =_xlfn.DAYS(TODAY(),B11) -> 103 | K11: 80 | L11: =K11+B11 -> 46070 | M11: =IF(H11<>"Delivered",_xlfn.DAYS(L11,TODAY()),"Delivered") -> -23 | N11: =VLOOKUP(F11,Table1[[#All],[Project Name]:[Balance(INR)]],8,0) -> 7500 | O11: 7500 | T11: Aditya
A12: =A11+1 -> 11 | B12: 45976 | C12: Chandan | D12: Testing-self | E12: 20000 | F12: Easy Rasta | G12: Dennis Anthony | H12: Testing | J12: =_xlfn.DAYS(TODAY(),B12) -> 117 | K12: 90 | L12: =K12+B12 -> 46066 | M12: =IF(H12<>"Delivered",_xlfn.DAYS(L12,TODAY()),"Delivered") -> -27 | N12: =VLOOKUP(F12,Table1[[#All],[Project Name]:[Balance(INR)]],8,0) -> 75000 | O12: 30000 | T12: Aditya
A13: =A12+1 -> 12 | B13: 45992 | C13: Vansh | D13: Testing-self | E13: 0 | F13: Real estate Data Management | G13: Akash Tripathi | H13: API Integration | J13: =_xlfn.DAYS(TODAY(),B13) -> 101 | K13: 40 | L13: =K13+B13 -> 46032 | M13: =IF(H13<>"Delivered",_xlfn.DAYS(L13,TODAY()),"Delivered") -> -61 | N13: =VLOOKUP(F13,Table1[[#All],[Project Name]:[Balance(INR)]],8,0) -> 24000 | O13: 24000 | T13: Vansh
A14: =A13+1 -> 13 | B14: 45982 | C14: Vansh | D14: Testing-self | E14: 0 | F14: SK Car Finance | G14: Prateek Srivastava | H14: Back end | J14: =_xlfn.DAYS(TODAY(),B14) -> 111 | K14: 90 | L14: =K14+B14 -> 46072 | M14: =IF(H14<>"Delivered",_xlfn.DAYS(L14,TODAY()),"Delivered") -> -21 | N14: =VLOOKUP(F14,Table1[[#All],[Project Name]:[Balance(INR)]],8,0) -> 170000 | O14: 100000 | T14: Priyanka
A15: =A14+1 -> 14 | B15: 46002 | C15: Krishna | D15: Testing-self | E15: 10000 | F15: Engineered Hybrid Ride-Sharing Platform | G15: Srishylam Jadi | H15: Testing | J15: =_xlfn.DAYS(TODAY(),B15) -> 91 | K15: 60 | L15: =K15+B15 -> 46062 | M15: =IF(H15<>"Delivered",_xlfn.DAYS(L15,TODAY()),"Delivered") -> -31 | N15: =VLOOKUP(F15,Table1[[#All],[Project Name]:[Balance(INR)]],8,0) -> 49500 | O15: 49500 | T15: Ishika
A16: =A15+1 -> 15 | B16: 45908 | C16: Chandan | D16: Testing-self | E16: 0 | F16: Employee India | G16: Taufeeq | H16: Back end | J16: =_xlfn.DAYS(TODAY(),B16) -> 185 | K16: 90 | L16: =K16+B16 -> 45998 | M16: =IF(H16<>"Delivered",_xlfn.DAYS(L16,TODAY()),"Delivered") -> -95 | N16: =VLOOKUP(F16,Table1[[#All],[Project Name]:[Balance(INR)]],8,0) -> 200000 | O16: 0
A17: =A16+1 -> 16 | B17: 45947 | C17: Krishna | D17: Testing-self | E17: 0 | F17: Eco Volt Solar | G17: Kuldeep | H17: Back end | J17: =_xlfn.DAYS(TODAY(),B17) -> 146 | K17: 50 | L17: =K17+B17 -> 45997 | M17: =IF(H17<>"Delivered",_xlfn.DAYS(L17,TODAY()),"Delivered") -> -96 | N17: =VLOOKUP(F17,Table1[[#All],[Project Name]:[Balance(INR)]],8,0) -> 30000 | O17: 0
A18: =A17+1 -> 17 | B18: 45986 | C18: Chandan | D18: not started | F18: NGK | G18: Strini Naidu | H18: Front end | J18: =_xlfn.DAYS(TODAY(),B18) -> 107 | K18: 90 | L18: =K18+B18 -> 46076 | M18: =IF(H18<>"Delivered",_xlfn.DAYS(L18,TODAY()),"Delivered") -> -17 | N18: =VLOOKUP(F18,Table1[[#All],[Project Name]:[Balance(INR)]],8,0) -> 82888.68 | O18: 0
A19: =A18+1 -> 18 | B19: 45996 | C19: Vansh | D19: Testing-self | E19: 0 | F19: Digital Poster App | G19: Gaurav Shashti | H19: Front end | J19: =_xlfn.DAYS(TODAY(),B19) -> 97 | K19: 60 | L19: =K19+B19 -> 46056 | M19: =IF(H19<>"Delivered",_xlfn.DAYS(L19,TODAY()),"Delivered") -> -37 | N19: =VLOOKUP(F19,Table1[[#All],[Project Name]:[Balance(INR)]],8,0) -> 115000 | O19: 0
A20: =A19+1 -> 19 | B20: 46006 | C20: Vansh | D20: Testing-self | E20: 0 | F20: OTT App | G20: VanLal | H20: Front end | J20: =_xlfn.DAYS(TODAY(),B20) -> 87 | K20: 45 | L20: =K20+B20 -> 46051 | M20: =IF(H20<>"Delivered",_xlfn.DAYS(L20,TODAY()),"Delivered") -> -42 | N20: =VLOOKUP(F20,Table1[[#All],[Project Name]:[Balance(INR)]],8,0) -> 50000 | O20: 0 | Q20: Yes
A21: =A20+1 -> 20 | B21: 46020 | C21: Vansh | D21: not started | F21: Taxi App | G21: Md Aslam | H21: Not Started | J21: =_xlfn.DAYS(TODAY(),B21) -> 73 | K21: 60 | L21: =K21+B21 -> 46080 | M21: =IF(H21<>"Delivered",_xlfn.DAYS(L21,TODAY()),"Delivered") -> -13 | N21: =VLOOKUP(F21,Table1[[#All],[Project Name]:[Balance(INR)]],8,0) -> 94000
A22: =A21+1 -> 21 | B22: 45975 | C22: Chandan | D22: Testing-self | E22: 0 | F22: Enlightify | G22: Apoorv | H22: Not Started | J22: =_xlfn.DAYS(TODAY(),B22) -> 118 | L22: =K22+B22 -> 45975 | M22: =IF(H22<>"Delivered",_xlfn.DAYS(L22,TODAY()),"Delivered") -> -118 | N22: =VLOOKUP(F22,Table1[[#All],[Project Name]:[Balance(INR)]],8,0) -> 18000
A23: =A22+1 -> 22 | B23: 45964 | C23: Vansh | D23: not started | E23: 0 | F23: Soya Products-Ecom | G23: M M Mishra | H23: Not Started | J23: =_xlfn.DAYS(TODAY(),B23) -> 129 | L23: =K23+B23 -> 45964 | M23: =IF(H23<>"Delivered",_xlfn.DAYS(L23,TODAY()),"Delivered") -> -129 | N23: =VLOOKUP(F23,Table1[[#All],[Project Name]:[Balance(INR)]],8,0) -> 74000
A24: =A23+1 -> 23 | B24: 45929 | C24: Vansh | D24: not started | E24: 0 | F24: Indgrocart | G24: Rajesh | H24: Not Started | J24: =_xlfn.DAYS(TODAY(),B24) -> 164 | L24: =K24+B24 -> 45929 | M24: =IF(H24<>"Delivered",_xlfn.DAYS(L24,TODAY()),"Delivered") -> -164 | N24: =VLOOKUP(F24,Table1[[#All],[Project Name]:[Balance(INR)]],8,0) -> 70000
A25: =A24+1 -> 24 | B25: 46034 | C25: Vansh | D25: Not started | F25: Urban Elite | G25: Mahendra | H25: Testing | J25: =_xlfn.DAYS(TODAY(),B25) -> 59 | K25: 45 | L25: =K25+B25 -> 46079 | M25: =IF(H25<>"Delivered",_xlfn.DAYS(L25,TODAY()),"Delivered") -> -14 | N25: =VLOOKUP(F25,Table1[[#All],[Project Name]:[Balance(INR)]],8,0) -> 35000 | O25: 35000 | T25: Rishabh
A26: =A25+1 -> 25 | B26: 45940 | C26: Krishna | D26: Testing-self | E26: 7500 | F26: Fornix | G26: Venket | H26: Delivered | J26: =_xlfn.DAYS(TODAY(),B26) -> 153 | K26: 60 | L26: =K26+B26 -> 46000 | M26: =IF(H26<>"Delivered",_xlfn.DAYS(L26,TODAY()),"Delivered") -> Delivered | N26: =VLOOKUP(F26,Table1[[#All],[Project Name]:[Balance(INR)]],8,0) -> 0 | O26: 80000 | P26: 46030 | Q26: Yes
A27: =A26+1 -> 26 | B27: 45988 | C27: Chandan | D27: Testing-self | E27: 10000 | F27: Local Market Online | G27: Vinod Khosla | H27: Testing | J27: =_xlfn.DAYS(TODAY(),B27) -> 105 | K27: 90 | L27: =K27+B27 -> 46078 | M27: =IF(H27<>"Delivered",_xlfn.DAYS(L27,TODAY()),"Delivered") -> -15 | N27: =VLOOKUP(F27,Table1[[#All],[Project Name]:[Balance(INR)]],8,0) -> 60000 | O27: 60000 | Q27: Yes | T27: Vansh
A28: =A27+1 -> 27 | B28: 45946 | C28: Krishna | D28: Testing-self | E28: 0 | F28: Bla-Bla | G28: Prem Reddy | H28: Testing | J28: =_xlfn.DAYS(TODAY(),B28) -> 147 | K28: 108 | L28: =K28+B28 -> 46054 | M28: =IF(H28<>"Delivered",_xlfn.DAYS(L28,TODAY()),"Delivered") -> -39 | N28: =VLOOKUP(F28,Table1[[#All],[Project Name]:[Balance(INR)]],8,0) -> 35000 | O28: 35000 | T28: Priyanka
A29: =A28+1 -> 28 | B29: 46017 | C29: Chandan | D29: Testing-self | E29: 0 | F29: GamifyIAS | G29: Amogh | H29: Testing | J29: =_xlfn.DAYS(TODAY(),B29) -> 76 | K29: 15 | L29: =K29+B29 -> 46032 | M29: =IF(H29<>"Delivered",_xlfn.DAYS(L29,TODAY()),"Delivered") -> -61 | N29: =VLOOKUP(F29,Table1[[#All],[Project Name]:[Balance(INR)]],8,0) -> 31000 | O29: 31000 | T29: Dev
A30: =A29+1 -> 29 | B30: 45966 | C30: Krishna | D30: Client Server | E30: 0 | F30: Beingpetz | G30: Mahesh | H30: Delivered | J30: =_xlfn.DAYS(TODAY(),B30) -> 127 | K30: 12 | L30: =K30+B30 -> 45978 | M30: =IF(H30<>"Delivered",_xlfn.DAYS(L30,TODAY()),"Delivered") -> Delivered | N30: =VLOOKUP(F30,Table1[[#All],[Project Name]:[Balance(INR)]],8,0) -> 0 | O30: 15000 | P30: 46024
A31: =A30+1 -> 30 | B31: 45931 | C31: Vansh | D31: Testing-self | E31: 20000 | F31: MediConnect | G31: Brij | H31: Testing | J31: =_xlfn.DAYS(TODAY(),B31) -> 162 | K31: 90 | L31: =K31+B31 -> 46021 | M31: =IF(H31<>"Delivered",_xlfn.DAYS(L31,TODAY()),"Delivered") -> -72 | N31: =VLOOKUP(F31,Table1[[#All],[Project Name]:[Balance(INR)]],8,0) -> 79999 | O31: 80000 | T31: Vansh
A32: =A31+1 -> 31 | B32: 45973 | C32: Chandan | D32: Testing-self | E32: 0 | F32: Degree India | G32: Taufeeq | H32: Delivered | J32: =_xlfn.DAYS(TODAY(),B32) -> 120 | K32: 45 | L32: =K32+B32 -> 46018 | M32: =IF(H32<>"Delivered",_xlfn.DAYS(L32,TODAY()),"Delivered") -> Delivered | N32: =VLOOKUP(F32,Table1[[#All],[Project Name]:[Balance(INR)]],8,0) -> 0 | O32: 15000 | P32: 46027 | Q32: Yes
A33: =A32+1 -> 32 | B33: 45947 | C33: Krishna | D33: Testing-self | E33: 5000 | F33: Bhardwaj hospital | G33: Dr Arun | H33: Testing | J33: =_xlfn.DAYS(TODAY(),B33) -> 146 | K33: 50 | L33: =K33+B33 -> 45997 | M33: =IF(H33<>"Delivered",_xlfn.DAYS(L33,TODAY()),"Delivered") -> -96 | N33: =VLOOKUP(F33,Table1[[#All],[Project Name]:[Balance(INR)]],8,0) -> 22500 | O33: 22500 | Q33: Yes | T33: Priyanka
E35: =SUM(Table4[Maintenance-Amount]) -> 117500 | N35: =SUBTOTAL(9,N2:N33) -> 629499 | O35: =SUBTOTAL(9,O2:O33) -> 514500

Sheet Roles & Responsibilities
A3: Team Alignment | E3: Sno | F3: Team Vansh + Krishna | G3: Status | H3: Resource | I3: Team Chandan + Rishabh | J3: Status | K3: Resource
A4: Backend | B4: Dev | C4: Vansh | E4: 1 | F4: Fornix | G4: Pending | H4: Prashant | I4: Degree India | J4: Done | K4: N/A
A5: Backend | B5: Priyanka | C5: Chandan | E5: =E4+1 -> 2 | F5: Mediconnect | G5: Pending | H5: Vansh+Dev | I5: Bhardwaj Hospital | J5: Deployment | K5: N/A
A6: Mob | B6: Aditya | C6: Vansh | E6: =E5+1 -> 3 | F6: OTT App | G6: Deployment | H6: Vansh | I6: Eco Volt | J6: Pending from client
A7: Mob | B7: Shubham | C7: Chandan | E7: =E6+1 -> 4 | F7: Local Market | G7: Pending | H7: Vansh | I7: Bla Bla | J7: Pending | K7: Priyanka
A8: Mob | B8: Ishika | C8: Vansh | E8: =E7+1 -> 5 | F8: Beingpetz | G8: Done | I8: Employee India | J8: Pending | K8: Wait
A9: Mob | B9: Anup | C9: Chandan | E9: =E8+1 -> 6 | F9: Gamify | G9: Pending | I9: NGK | J9: Pending | K9: Chandan
A10: Mob | B10: Prashant | C10: Vansh | E10: =E9+1 -> 7 | F10: School Management | G10: Pending | H10: Aditya+Dev+Ishika(Admin) | I10: Hybrid Ride | J10: Pending | K10: Team(next)
A11: HR/Admin | B11: Ravleen | C11: Rishabh/Krishna | E11: =E10+1 -> 8 | F11: Real Estate | G11: Pending | H11: Vansh | I11: SK Finance | J11: Pending | K11: Anup
A12: Sales | B12: Haider | C12: Rishabh/Krishna | E12: =E11+1 -> 9 | F12: Digital Poster | G12: Pending | H12: Ishika(Admin)+Aditya(Frontend) | I12: FitLeap | J12: Pending | K12: Dubey
A13: Sales | B13: Ishika Rawal | C13: Rishabh/Krishna | E13: =E12+1 -> 10 | F13: Agriebook | G13: Done | I13: Urban Elite | J13: Pending | K13: Rishabh
A14: Sales | B14: Resource 2 | C14: Rishabh/Krishna | E14: =E13+1 -> 11 | F14: Easy Rasta | G14: Pending | H14: Dev+Prashant | I14: Stenna | J14: Pending | K14: Krishna/Rishabh
A15: Sales | B15: Resource 3 | C15: Rishabh/Krishna

Sheet Asset Purchase
A1: Sno | B1: Day | C1: Date | D1: Item | E1: Resource | F1: Paid By | G1: Amount | I1: Total | J1: =SUM(G:G) -> 25500
A2: 1 | B2: =TEXT(C2,"dddd") -> Monday | C2: 46062 | D2: Purchase of 2nd hand laptop | E2: Shubham Dubey | F2: Chandan | G2: 30500
A3: 1 | B3: =TEXT(C3,"dddd") -> Thursday | C3: 46065 | D3: received from dubey | E3: Shubham Dubey | F3: Chandan | G3: -5000
